{"lang": "DE", "input": {"massExportModelId": 2, "taxGroup": 88, "years": [2019, 2020, 2021], "incomes": [15000.0, 20000.0, 30000.0, 25000.0, 35000.0, 40000.0, 90000.0, 80000.0, 70000.0, 60000.0, 50000.0, 45000.0, 100000.0, 125000.0, 150000.0, 175000.0, 200000.0, 250000.0, 5000000.0, 1000000.0, 750000.0, 500000.0, 400000.0, 300000.0, 10000000.0, 50000000.0, 100000000.0], "fortunes": [], "confession": 5, "klasse": 1, "belastungsVergleich": 1, "output": 1, "considerMaximumExposureLimit": false}, "model": {"name": "Ledig (mit 1 Kind)", "relationship": 1, "children": [3], "age1": 35, "age2": 0, "revenueType1": 1, "revenueType2": 0, "revenuePercent1": 100.0, "revenuePercent2": 0.0}, "output": "json", "payload": [{"bfsId": 261, "municipality": "Zürich", "canton": "ZH", "cantonId": 1, "income": 15000.0, "values": [24.0, 24.0, 24.0]}, {"bfsId": 261, "municipality": "Zürich", "canton": "ZH", "cantonId": 1, "income": 20000.0, "values": [24.0, 24.0, 24.0]}, {"bfsId": 261, "municipality": "Zürich", "canton": "ZH", "cantonId": 1, "income": 25000.0, "values": [24.0, 24.0, 24.0]}, {"bfsId": 261, "municipality": "Zürich", "canton": "ZH", "cantonId": 1, "income": 30000.0, "values": [24.0, 24.0, 24.0]}, {"bfsId": 261, "municipality": "Zürich", "canton": "ZH", "cantonId": 1, "income": 35000.0, "values": [186.0, 186.0, 186.0]}, {"bfsId": 261, "municipality": "Zürich", "canton": "ZH", "cantonId": 1, "income": 40000.0, "values": [423.0, 423.0, 423.0]}, {"bfsId": 261, "municipality": "Zürich", "canton": "ZH", "cantonId": 1, "income": 45000.0, "values": [718.0, 712.0, 712.0]}, {"bfsId": 261, "municipality": "Zürich", "canton": "ZH", "cantonId": 1, "income": 50000.0, "values": [1077.0, 1069.0, 1069.0]}, {"bfsId": 261, "municipality": "Zürich", "canton": "ZH", "cantonId": 1, "income": 60000.0, "values": [1905.0, 1894.0, 1894.0]}, {"bfsId": 261, "municipality": "Zürich", "canton": "ZH", "cantonId": 1, "income": 70000.0, "values": [2897.0, 2884.0, 2871.0]}, {"bfsId": 261, "municipality": "Zürich", "canton": "ZH", "cantonId": 1, "income": 80000.0, "values": [4224.0, 4208.0, 4208.0]}, {"bfsId": 261, "municipality": "Zürich", "canton": "ZH", "cantonId": 1, "income": 90000.0, "values": [5720.0, 5684.0, 5684.0]}, {"bfsId": 261, "municipality": "Zürich", "canton": "ZH", "cantonId": 1, "income": 100000.0, "values": [7344.0, 7306.0, 7306.0]}, {"bfsId": 261, "municipality": "Zürich", "canton": "ZH", "cantonId": 1, "income": 125000.0, "values": [11741.0, 11696.0, 11696.0]}, {"bfsId": 261, "municipality": "Zürich", "canton": "ZH", "cantonId": 1, "income": 150000.0, "values": [16905.0, 16856.0, 16856.0]}, {"bfsId": 261, "municipality": "Zürich", "canton": "ZH", "cantonId": 1, "income": 175000.0, "values": [23338.0, 23243.0, 23243.0]}, {"bfsId": 261, "municipality": "Zürich", "canton": "ZH", "cantonId": 1, "income": 200000.0, "values": [30759.0, 30661.0, 30628.0]}, {"bfsId": 261, "municipality": "Zürich", "canton": "ZH", "cantonId": 1, "income": 250000.0, "values": [46472.0, 46333.0, 46333.0]}, {"bfsId": 261, "municipality": "Zürich", "canton": "ZH", "cantonId": 1, "income": 300000.0, "values": [62998.0, 62813.0, 62775.0]}, {"bfsId": 261, "municipality": "Zürich", "canton": "ZH", "cantonId": 1, "income": 400000.0, "values": [97994.0, 97758.0, 97719.0]}, {"bfsId": 261, "municipality": "Zürich", "canton": "ZH", "cantonId": 1, "income": 500000.0, "values": [135491.0, 135201.0, 135118.0]}, {"bfsId": 261, "municipality": "Zürich", "canton": "ZH", "cantonId": 1, "income": 750000.0, "values": [229711.0, 229255.0, 229172.0]}, {"bfsId": 261, "municipality": "Zürich", "canton": "ZH", "cantonId": 1, "income": 1000000.0, "values": [323931.0, 323309.0, 323184.0]}, {"bfsId": 261, "municipality": "Zürich", "canton": "ZH", "cantonId": 1, "income": 5000000.0, "values": [1776864.0, 1773866.0, 1773347.0]}, {"bfsId": 261, "municipality": "Zürich", "canton": "ZH", "cantonId": 1, "income": 10000000.0, "values": [3592981.0, 3586985.0, 3585986.0]}, {"bfsId": 261, "municipality": "Zürich", "canton": "ZH", "cantonId": 1, "income": 50000000.0, "values": [18122076.0, 18092098.0, 18087102.0]}, {"bfsId": 261, "municipality": "Zürich", "canton": "ZH", "cantonId": 1, "income": 100000000.0, "values": [36283445.0, 36223490.0, 36213497.0]}, {"bfsId": 351, "municipality": "Bern", "canton": "BE", "cantonId": 2, "income": 15000.0, "values": [0.0, 0.0, 0.0]}, {"bfsId": 351, "municipality": "Bern", "canton": "BE", "cantonId": 2, "income": 20000.0, "values": [0.0, 0.0, 0.0]}, {"bfsId": 351, "municipality": "Bern", "canton": "BE", "cantonId": 2, "income": 25000.0, "values": [0.0, 0.0, 0.0]}, {"bfsId": 351, "municipality": "Bern", "canton": "BE", "cantonId": 2, "income": 30000.0, "values": [312.0, 312.0, 309.0]}, {"bfsId": 351, "municipality": "Bern", "canton": "BE", "cantonId": 2, "income": 35000.0, "values": [784.0, 784.0, 778.0]}, {"bfsId": 351, "municipality": "Bern", "canton": "BE", "cantonId": 2, "income": 40000.0, "values": [1361.0, 1361.0, 1351.0]}, {"bfsId": 351, "municipality": "Bern", "canton": "BE", "cantonId": 2, "income": 45000.0, "values": [2075.0, 2058.0, 2042.0]}, {"bfsId": 351, "municipality": "Bern", "canton": "BE", "cantonId": 2, "income": 50000.0, "values": [2864.0, 2847.0, 2825.0]}, {"bfsId": 351, "municipality": "Bern", "canton": "BE", "cantonId": 2, "income": 60000.0, "values": [4449.0, 4432.0, 4398.0]}, {"bfsId": 351, "municipality": "Bern", "canton": "BE", "cantonId": 2, "income": 70000.0, "values": [6057.0, 6040.0, 5976.0]}, {"bfsId": 351, "municipality": "Bern", "canton": "BE", "cantonId": 2, "income": 80000.0, "values": [7757.0, 7737.0, 7679.0]}, {"bfsId": 351, "municipality": "Bern", "canton": "BE", "cantonId": 2, "income": 90000.0, "values": [9581.0, 9535.0, 9466.0]}, {"bfsId": 351, "municipality": "Bern", "canton": "BE", "cantonId": 2, "income": 100000.0, "values": [11591.0, 11544.0, 11462.0]}, {"bfsId": 351, "municipality": "Bern", "canton": "BE", "cantonId": 2, "income": 125000.0, "values": [17040.0, 16985.0, 16869.0]}, {"bfsId": 351, "municipality": "Bern", "canton": "BE", "cantonId": 2, "income": 150000.0, "values": [23292.0, 23230.0, 23077.0]}, {"bfsId": 351, "municipality": "Bern", "canton": "BE", "cantonId": 2, "income": 175000.0, "values": [30796.0, 30688.0, 30493.0]}, {"bfsId": 351, "municipality": "Bern", "canton": "BE", "cantonId": 2, "income": 200000.0, "values": [39690.0, 39573.0, 39294.0]}, {"bfsId": 351, "municipality": "Bern", "canton": "BE", "cantonId": 2, "income": 250000.0, "values": [57691.0, 57532.0, 57200.0]}, {"bfsId": 351, "municipality": "Bern", "canton": "BE", "cantonId": 2, "income": 300000.0, "values": [75951.0, 75749.0, 75284.0]}, {"bfsId": 351, "municipality": "Bern", "canton": "BE", "cantonId": 2, "income": 400000.0, "values": [113391.0, 113136.0, 112474.0]}, {"bfsId": 351, "municipality": "Bern", "canton": "BE", "cantonId": 2, "income": 500000.0, "values": [151969.0, 151672.0, 150763.0]}, {"bfsId": 351, "municipality": "Bern", "canton": "BE", "cantonId": 2, "income": 750000.0, "values": [249278.0, 248806.0, 247382.0]}, {"bfsId": 351, "municipality": "Bern", "canton": "BE", "cantonId": 2, "income": 1000000.0, "values": [346747.0, 346103.0, 344121.0]}, {"bfsId": 351, "municipality": "Bern", "canton": "BE", "cantonId": 2, "income": 5000000.0, "values": [1851661.0, 1848556.0, 1837910.0]}, {"bfsId": 351, "municipality": "Bern", "canton": "BE", "cantonId": 2, "income": 10000000.0, "values": [3732752.0, 3726543.0, 3705083.0]}, {"bfsId": 351, "municipality": "Bern", "canton": "BE", "cantonId": 2, "income": 50000000.0, "values": [18781652.0, 18750603.0, 18642466.0]}, {"bfsId": 351, "municipality": "Bern", "canton": "BE", "cantonId": 2, "income": 100000000.0, "values": [37592778.0, 37530678.0, 37314195.0]}, {"bfsId": 1061, "municipality": "Luzern", "canton": "LU", "cantonId": 3, "income": 15000.0, "values": [50.0, 50.0, 50.0]}, {"bfsId": 1061, "municipality": "Luzern", "canton": "LU", "cantonId": 3, "income": 20000.0, "values": [50.0, 50.0, 50.0]}, {"bfsId": 1061, "municipality": "Luzern", "canton": "LU", "cantonId": 3, "income": 25000.0, "values": [50.0, 50.0, 50.0]}, {"bfsId": 1061, "municipality": "Luzern", "canton": "LU", "cantonId": 3, "income": 30000.0, "values": [50.0, 50.0, 50.0]}, {"bfsId": 1061, "municipality": "Luzern", "canton": "LU", "cantonId": 3, "income": 35000.0, "values": [57.0, 57.0, 57.0]}, {"bfsId": 1061, "municipality": "Luzern", "canton": "LU", "cantonId": 3, "income": 40000.0, "values": [164.0, 164.0, 164.0]}, {"bfsId": 1061, "municipality": "Luzern", "canton": "LU", "cantonId": 3, "income": 45000.0, "values": [628.0, 616.0, 616.0]}, {"bfsId": 1061, "municipality": "Luzern", "canton": "LU", "cantonId": 3, "income": 50000.0, "values": [1218.0, 1203.0, 1203.0]}, {"bfsId": 1061, "municipality": "Luzern", "canton": "LU", "cantonId": 3, "income": 60000.0, "values": [2584.0, 2569.0, 2569.0]}, {"bfsId": 1061, "municipality": "Luzern", "canton": "LU", "cantonId": 3, "income": 70000.0, "values": [3966.0, 3950.0, 3935.0]}, {"bfsId": 1061, "municipality": "Luzern", "canton": "LU", "cantonId": 3, "income": 80000.0, "values": [5498.0, 5480.0, 5480.0]}, {"bfsId": 1061, "municipality": "Luzern", "canton": "LU", "cantonId": 3, "income": 90000.0, "values": [7110.0, 7073.0, 7073.0]}, {"bfsId": 1061, "municipality": "Luzern", "canton": "LU", "cantonId": 3, "income": 100000.0, "values": [8750.0, 8711.0, 8711.0]}, {"bfsId": 1061, "municipality": "Luzern", "canton": "LU", "cantonId": 3, "income": 125000.0, "values": [13176.0, 13132.0, 13132.0]}, {"bfsId": 1061, "municipality": "Luzern", "canton": "LU", "cantonId": 3, "income": 150000.0, "values": [18281.0, 18233.0, 18233.0]}, {"bfsId": 1061, "municipality": "Luzern", "canton": "LU", "cantonId": 3, "income": 175000.0, "values": [24472.0, 24380.0, 24380.0]}, {"bfsId": 1061, "municipality": "Luzern", "canton": "LU", "cantonId": 3, "income": 200000.0, "values": [31879.0, 31780.0, 31747.0]}, {"bfsId": 1061, "municipality": "Luzern", "canton": "LU", "cantonId": 3, "income": 250000.0, "values": [46865.0, 46733.0, 46733.0]}, {"bfsId": 1061, "municipality": "Luzern", "canton": "LU", "cantonId": 3, "income": 300000.0, "values": [61885.0, 61720.0, 61687.0]}, {"bfsId": 1061, "municipality": "Luzern", "canton": "LU", "cantonId": 3, "income": 400000.0, "values": [91858.0, 91660.0, 91627.0]}, {"bfsId": 1061, "municipality": "Luzern", "canton": "LU", "cantonId": 3, "income": 500000.0, "values": [121865.0, 121634.0, 121567.0]}, {"bfsId": 1061, "municipality": "Luzern", "canton": "LU", "cantonId": 3, "income": 750000.0, "values": [196863.0, 196500.0, 196434.0]}, {"bfsId": 1061, "municipality": "Luzern", "canton": "LU", "cantonId": 3, "income": 1000000.0, "values": [271862.0, 271367.0, 271268.0]}, {"bfsId": 1061, "municipality": "Luzern", "canton": "LU", "cantonId": 3, "income": 5000000.0, "values": [1395343.0, 1393031.0, 1392631.0]}, {"bfsId": 1061, "municipality": "Luzern", "canton": "LU", "cantonId": 3, "income": 10000000.0, "values": [2795712.0, 2791088.0, 2790318.0]}, {"bfsId": 1061, "municipality": "Luzern", "canton": "LU", "cantonId": 3, "income": 50000000.0, "values": [13998782.0, 13975666.0, 13971814.0]}, {"bfsId": 1061, "municipality": "Luzern", "canton": "LU", "cantonId": 3, "income": 100000000.0, "values": [28002620.0, 27956389.0, 27948684.0]}, {"bfsId": 1201, "municipality": "Altdorf (UR)", "canton": "UR", "cantonId": 4, "income": 15000.0, "values": [70.0, 70.0, 70.0]}, {"bfsId": 1201, "municipality": "Altdorf (UR)", "canton": "UR", "cantonId": 4, "income": 20000.0, "values": [70.0, 70.0, 70.0]}, {"bfsId": 1201, "municipality": "Altdorf (UR)", "canton": "UR", "cantonId": 4, "income": 25000.0, "values": [70.0, 70.0, 70.0]}, {"bfsId": 1201, "municipality": "Altdorf (UR)", "canton": "UR", "cantonId": 4, "income": 30000.0, "values": [70.0, 70.0, 70.0]}, {"bfsId": 1201, "municipality": "Altdorf (UR)", "canton": "UR", "cantonId": 4, "income": 35000.0, "values": [70.0, 70.0, 70.0]}, {"bfsId": 1201, "municipality": "Altdorf (UR)", "canton": "UR", "cantonId": 4, "income": 40000.0, "values": [637.0, 628.0, 628.0]}, {"bfsId": 1201, "municipality": "Altdorf (UR)", "canton": "UR", "cantonId": 4, "income": 45000.0, "values": [1248.0, 1240.0, 1240.0]}, {"bfsId": 1201, "municipality": "Altdorf (UR)", "canton": "UR", "cantonId": 4, "income": 50000.0, "values": [1860.0, 1850.0, 1850.0]}, {"bfsId": 1201, "municipality": "Altdorf (UR)", "canton": "UR", "cantonId": 4, "income": 60000.0, "values": [3084.0, 3071.0, 3071.0]}, {"bfsId": 1201, "municipality": "Altdorf (UR)", "canton": "UR", "cantonId": 4, "income": 70000.0, "values": [4307.0, 4293.0, 4292.0]}, {"bfsId": 1201, "municipality": "Altdorf (UR)", "canton": "UR", "cantonId": 4, "income": 80000.0, "values": [5706.0, 5687.0, 5685.0]}, {"bfsId": 1201, "municipality": "Altdorf (UR)", "canton": "UR", "cantonId": 4, "income": 90000.0, "values": [7164.0, 7139.0, 7136.0]}, {"bfsId": 1201, "municipality": "Altdorf (UR)", "canton": "UR", "cantonId": 4, "income": 100000.0, "values": [8661.0, 8632.0, 8629.0]}, {"bfsId": 1201, "municipality": "Altdorf (UR)", "canton": "UR", "cantonId": 4, "income": 125000.0, "values": [12647.0, 12611.0, 12607.0]}, {"bfsId": 1201, "municipality": "Altdorf (UR)", "canton": "UR", "cantonId": 4, "income": 150000.0, "values": [17018.0, 16973.0, 16967.0]}, {"bfsId": 1201, "municipality": "Altdorf (UR)", "canton": "UR", "cantonId": 4, "income": 175000.0, "values": [22214.0, 22142.0, 22136.0]}, {"bfsId": 1201, "municipality": "Altdorf (UR)", "canton": "UR", "cantonId": 4, "income": 200000.0, "values": [28307.0, 28226.0, 28206.0]}, {"bfsId": 1201, "municipality": "Altdorf (UR)", "canton": "UR", "cantonId": 4, "income": 250000.0, "values": [40499.0, 40395.0, 40387.0]}, {"bfsId": 1201, "municipality": "Altdorf (UR)", "canton": "UR", "cantonId": 4, "income": 300000.0, "values": [52705.0, 52578.0, 52555.0]}, {"bfsId": 1201, "municipality": "Altdorf (UR)", "canton": "UR", "cantonId": 4, "income": 400000.0, "values": [77091.0, 76930.0, 76903.0]}, {"bfsId": 1201, "municipality": "Altdorf (UR)", "canton": "UR", "cantonId": 4, "income": 500000.0, "values": [101489.0, 101295.0, 101251.0]}, {"bfsId": 1201, "municipality": "Altdorf (UR)", "canton": "UR", "cantonId": 4, "income": 750000.0, "values": [162480.0, 162181.0, 162128.0]}, {"bfsId": 1201, "municipality": "Altdorf (UR)", "canton": "UR", "cantonId": 4, "income": 1000000.0, "values": [223470.0, 223067.0, 222994.0]}, {"bfsId": 1201, "municipality": "Altdorf (UR)", "canton": "UR", "cantonId": 4, "income": 5000000.0, "values": [1144785.0, 1142883.0, 1142561.0]}, {"bfsId": 1201, "municipality": "Altdorf (UR)", "canton": "UR", "cantonId": 4, "income": 10000000.0, "values": [2296391.0, 2292590.0, 2291957.0]}, {"bfsId": 1201, "municipality": "Altdorf (UR)", "canton": "UR", "cantonId": 4, "income": 50000000.0, "values": [11509299.0, 11490290.0, 11487123.0]}, {"bfsId": 1201, "municipality": "Altdorf (UR)", "canton": "UR", "cantonId": 4, "income": 100000000.0, "values": [23025434.0, 22987417.0, 22981081.0]}, {"bfsId": 1372, "municipality": "Schwyz", "canton": "SZ", "cantonId": 5, "income": 15000.0, "values": [0.0, 0.0, 0.0]}, {"bfsId": 1372, "municipality": "Schwyz", "canton": "SZ", "cantonId": 5, "income": 20000.0, "values": [0.0, 0.0, 0.0]}, {"bfsId": 1372, "municipality": "Schwyz", "canton": "SZ", "cantonId": 5, "income": 25000.0, "values": [0.0, 0.0, 0.0]}, {"bfsId": 1372, "municipality": "Schwyz", "canton": "SZ", "cantonId": 5, "income": 30000.0, "values": [1.0, 0.0, 0.0]}, {"bfsId": 1372, "municipality": "Schwyz", "canton": "SZ", "cantonId": 5, "income": 35000.0, "values": [69.0, 63.0, 66.0]}, {"bfsId": 1372, "municipality": "Schwyz", "canton": "SZ", "cantonId": 5, "income": 40000.0, "values": [284.0, 273.0, 273.0]}, {"bfsId": 1372, "municipality": "Schwyz", "canton": "SZ", "cantonId": 5, "income": 45000.0, "values": [665.0, 630.0, 630.0]}, {"bfsId": 1372, "municipality": "Schwyz", "canton": "SZ", "cantonId": 5, "income": 50000.0, "values": [1104.0, 1051.0, 1051.0]}, {"bfsId": 1372, "municipality": "Schwyz", "canton": "SZ", "cantonId": 5, "income": 60000.0, "values": [2078.0, 1985.0, 1985.0]}, {"bfsId": 1372, "municipality": "Schwyz", "canton": "SZ", "cantonId": 5, "income": 70000.0, "values": [3161.0, 3024.0, 3012.0]}, {"bfsId": 1372, "municipality": "Schwyz", "canton": "SZ", "cantonId": 5, "income": 80000.0, "values": [4506.0, 4321.0, 4321.0]}, {"bfsId": 1372, "municipality": "Schwyz", "canton": "SZ", "cantonId": 5, "income": 90000.0, "values": [5979.0, 5742.0, 5728.0]}, {"bfsId": 1372, "municipality": "Schwyz", "canton": "SZ", "cantonId": 5, "income": 100000.0, "values": [7569.0, 7264.0, 7264.0]}, {"bfsId": 1372, "municipality": "Schwyz", "canton": "SZ", "cantonId": 5, "income": 125000.0, "values": [11873.0, 11433.0, 11419.0]}, {"bfsId": 1372, "municipality": "Schwyz", "canton": "SZ", "cantonId": 5, "income": 150000.0, "values": [16538.0, 15964.0, 15964.0]}, {"bfsId": 1372, "municipality": "Schwyz", "canton": "SZ", "cantonId": 5, "income": 175000.0, "values": [21968.0, 21224.0, 21224.0]}, {"bfsId": 1372, "municipality": "Schwyz", "canton": "SZ", "cantonId": 5, "income": 200000.0, "values": [28279.0, 27399.0, 27372.0]}, {"bfsId": 1372, "municipality": "Schwyz", "canton": "SZ", "cantonId": 5, "income": 250000.0, "values": [40909.0, 39737.0, 39737.0]}, {"bfsId": 1372, "municipality": "Schwyz", "canton": "SZ", "cantonId": 5, "income": 300000.0, "values": [54083.0, 52561.0, 52530.0]}, {"bfsId": 1372, "municipality": "Schwyz", "canton": "SZ", "cantonId": 5, "income": 400000.0, "values": [83348.0, 80994.0, 80962.0]}, {"bfsId": 1372, "municipality": "Schwyz", "canton": "SZ", "cantonId": 5, "income": 500000.0, "values": [111432.0, 108342.0, 108285.0]}, {"bfsId": 1372, "municipality": "Schwyz", "canton": "SZ", "cantonId": 5, "income": 750000.0, "values": [177388.0, 172634.0, 172577.0]}, {"bfsId": 1372, "municipality": "Schwyz", "canton": "SZ", "cantonId": 5, "income": 1000000.0, "values": [243344.0, 236926.0, 236840.0]}, {"bfsId": 1372, "municipality": "Schwyz", "canton": "SZ", "cantonId": 5, "income": 5000000.0, "values": [1244084.0, 1211268.0, 1210919.0]}, {"bfsId": 1372, "municipality": "Schwyz", "canton": "SZ", "cantonId": 5, "income": 10000000.0, "values": [2494964.0, 2429124.0, 2428453.0]}, {"bfsId": 1372, "municipality": "Schwyz", "canton": "SZ", "cantonId": 5, "income": 50000000.0, "values": [12502119.0, 12172082.0, 12168726.0]}, {"bfsId": 1372, "municipality": "Schwyz", "canton": "SZ", "cantonId": 5, "income": 100000000.0, "values": [25011063.0, 24350779.0, 24344067.0]}, {"bfsId": 1407, "municipality": "Sarnen", "canton": "OW", "cantonId": 6, "income": 15000.0, "values": [0.0, 0.0, 0.0]}, {"bfsId": 1407, "municipality": "Sarnen", "canton": "OW", "cantonId": 6, "income": 20000.0, "values": [0.0, 0.0, 0.0]}, {"bfsId": 1407, "municipality": "Sarnen", "canton": "OW", "cantonId": 6, "income": 25000.0, "values": [0.0, 0.0, 0.0]}, {"bfsId": 1407, "municipality": "Sarnen", "canton": "OW", "cantonId": 6, "income": 30000.0, "values": [0.0, 0.0, 0.0]}, {"bfsId": 1407, "municipality": "Sarnen", "canton": "OW", "cantonId": 6, "income": 35000.0, "values": [0.0, 0.0, 0.0]}, {"bfsId": 1407, "municipality": "Sarnen", "canton": "OW", "cantonId": 6, "income": 40000.0, "values": [345.0, 346.0, 346.0]}, {"bfsId": 1407, "municipality": "Sarnen", "canton": "OW", "cantonId": 6, "income": 45000.0, "values": [858.0, 845.0, 845.0]}, {"bfsId": 1407, "municipality": "Sarnen", "canton": "OW", "cantonId": 6, "income": 50000.0, "values": [1369.0, 1356.0, 1356.0]}, {"bfsId": 1407, "municipality": "Sarnen", "canton": "OW", "cantonId": 6, "income": 60000.0, "values": [2380.0, 2381.0, 2368.0]}, {"bfsId": 1407, "municipality": "Sarnen", "canton": "OW", "cantonId": 6, "income": 70000.0, "values": [3622.0, 3609.0, 3609.0]}, {"bfsId": 1407, "municipality": "Sarnen", "canton": "OW", "cantonId": 6, "income": 80000.0, "values": [5048.0, 5019.0, 5019.0]}, {"bfsId": 1407, "municipality": "Sarnen", "canton": "OW", "cantonId": 6, "income": 90000.0, "values": [6524.0, 6492.0, 6492.0]}, {"bfsId": 1407, "municipality": "Sarnen", "canton": "OW", "cantonId": 6, "income": 100000.0, "values": [8043.0, 8009.0, 8009.0]}, {"bfsId": 1407, "municipality": "Sarnen", "canton": "OW", "cantonId": 6, "income": 125000.0, "values": [11993.0, 11958.0, 11958.0]}, {"bfsId": 1407, "municipality": "Sarnen", "canton": "OW", "cantonId": 6, "income": 150000.0, "values": [16128.0, 16090.0, 16090.0]}, {"bfsId": 1407, "municipality": "Sarnen", "canton": "OW", "cantonId": 6, "income": 175000.0, "values": [21098.0, 21023.0, 21023.0]}, {"bfsId": 1407, "municipality": "Sarnen", "canton": "OW", "cantonId": 6, "income": 200000.0, "values": [26950.0, 26872.0, 26846.0]}, {"bfsId": 1407, "municipality": "Sarnen", "canton": "OW", "cantonId": 6, "income": 250000.0, "values": [38662.0, 38559.0, 38559.0]}, {"bfsId": 1407, "municipality": "Sarnen", "canton": "OW", "cantonId": 6, "income": 300000.0, "values": [50401.0, 50271.0, 50245.0]}, {"bfsId": 1407, "municipality": "Sarnen", "canton": "OW", "cantonId": 6, "income": 400000.0, "values": [73825.0, 73670.0, 73645.0]}, {"bfsId": 1407, "municipality": "Sarnen", "canton": "OW", "cantonId": 6, "income": 500000.0, "values": [97275.0, 97095.0, 97043.0]}, {"bfsId": 1407, "municipality": "Sarnen", "canton": "OW", "cantonId": 6, "income": 750000.0, "values": [155888.0, 155605.0, 155553.0]}, {"bfsId": 1407, "municipality": "Sarnen", "canton": "OW", "cantonId": 6, "income": 1000000.0, "values": [214502.0, 214114.0, 214037.0]}, {"bfsId": 1407, "municipality": "Sarnen", "canton": "OW", "cantonId": 6, "income": 5000000.0, "values": [1097758.0, 1095935.0, 1095619.0]}, {"bfsId": 1407, "municipality": "Sarnen", "canton": "OW", "cantonId": 6, "income": 10000000.0, "values": [2201785.0, 2198140.0, 2197534.0]}, {"bfsId": 1407, "municipality": "Sarnen", "canton": "OW", "cantonId": 6, "income": 50000000.0, "values": [11034108.0, 11015884.0, 11012848.0]}, {"bfsId": 1407, "municipality": "Sarnen", "canton": "OW", "cantonId": 6, "income": 100000000.0, "values": [22074513.0, 22038065.0, 22031991.0]}, {"bfsId": 1509, "municipality": "Stans", "canton": "NW", "cantonId": 7, "income": 15000.0, "values": [50.0, 50.0, 50.0]}, {"bfsId": 1509, "municipality": "Stans", "canton": "NW", "cantonId": 7, "income": 20000.0, "values": [50.0, 50.0, 50.0]}, {"bfsId": 1509, "municipality": "Stans", "canton": "NW", "cantonId": 7, "income": 25000.0, "values": [50.0, 50.0, 50.0]}, {"bfsId": 1509, "municipality": "Stans", "canton": "NW", "cantonId": 7, "income": 30000.0, "values": [50.0, 50.0, 50.0]}, {"bfsId": 1509, "municipality": "Stans", "canton": "NW", "cantonId": 7, "income": 35000.0, "values": [50.0, 50.0, 50.0]}, {"bfsId": 1509, "municipality": "Stans", "canton": "NW", "cantonId": 7, "income": 40000.0, "values": [144.0, 144.0, 127.0]}, {"bfsId": 1509, "municipality": "Stans", "canton": "NW", "cantonId": 7, "income": 45000.0, "values": [362.0, 361.0, 326.0]}, {"bfsId": 1509, "municipality": "Stans", "canton": "NW", "cantonId": 7, "income": 50000.0, "values": [682.0, 680.0, 622.0]}, {"bfsId": 1509, "municipality": "Stans", "canton": "NW", "cantonId": 7, "income": 60000.0, "values": [1593.0, 1571.0, 1502.0]}, {"bfsId": 1509, "municipality": "Stans", "canton": "NW", "cantonId": 7, "income": 70000.0, "values": [2769.0, 2747.0, 2665.0]}, {"bfsId": 1509, "municipality": "Stans", "canton": "NW", "cantonId": 7, "income": 80000.0, "values": [4168.0, 4157.0, 4072.0]}, {"bfsId": 1509, "municipality": "Stans", "canton": "NW", "cantonId": 7, "income": 90000.0, "values": [5691.0, 5656.0, 5570.0]}, {"bfsId": 1509, "municipality": "Stans", "canton": "NW", "cantonId": 7, "income": 100000.0, "values": [7241.0, 7225.0, 7118.0]}, {"bfsId": 1509, "municipality": "Stans", "canton": "NW", "cantonId": 7, "income": 125000.0, "values": [11413.0, 11393.0, 11283.0]}, {"bfsId": 1509, "municipality": "Stans", "canton": "NW", "cantonId": 7, "income": 150000.0, "values": [16043.0, 15998.0, 15908.0]}, {"bfsId": 1509, "municipality": "Stans", "canton": "NW", "cantonId": 7, "income": 175000.0, "values": [21546.0, 21462.0, 21371.0]}, {"bfsId": 1509, "municipality": "Stans", "canton": "NW", "cantonId": 7, "income": 200000.0, "values": [28078.0, 27996.0, 27870.0]}, {"bfsId": 1509, "municipality": "Stans", "canton": "NW", "cantonId": 7, "income": 250000.0, "values": [41209.0, 41093.0, 40990.0]}, {"bfsId": 1509, "municipality": "Stans", "canton": "NW", "cantonId": 7, "income": 300000.0, "values": [54565.0, 54416.0, 54288.0]}, {"bfsId": 1509, "municipality": "Stans", "canton": "NW", "cantonId": 7, "income": 400000.0, "values": [80086.0, 79923.0, 79812.0]}, {"bfsId": 1509, "municipality": "Stans", "canton": "NW", "cantonId": 7, "income": 500000.0, "values": [104676.0, 104487.0, 104349.0]}, {"bfsId": 1509, "municipality": "Stans", "canton": "NW", "cantonId": 7, "income": 750000.0, "values": [166140.0, 165842.0, 165704.0]}, {"bfsId": 1509, "municipality": "Stans", "canton": "NW", "cantonId": 7, "income": 1000000.0, "values": [227603.0, 227197.0, 227032.0]}, {"bfsId": 1509, "municipality": "Stans", "canton": "NW", "cantonId": 7, "income": 5000000.0, "values": [1156460.0, 1154543.0, 1154127.0]}, {"bfsId": 1509, "municipality": "Stans", "canton": "NW", "cantonId": 7, "income": 10000000.0, "values": [2317489.0, 2313656.0, 2312934.0]}, {"bfsId": 1509, "municipality": "Stans", "canton": "NW", "cantonId": 7, "income": 50000000.0, "values": [11605822.0, 11586658.0, 11583381.0]}, {"bfsId": 1509, "municipality": "Stans", "canton": "NW", "cantonId": 7, "income": 100000000.0, "values": [23216240.0, 23177912.0, 23171439.0]}, {"bfsId": 1632, "municipality": "Glarus", "canton": "GL", "cantonId": 8, "income": 15000.0, "values": [0.0, 0.0, 0.0]}, {"bfsId": 1632, "municipality": "Glarus", "canton": "GL", "cantonId": 8, "income": 20000.0, "values": [0.0, 0.0, 0.0]}, {"bfsId": 1632, "municipality": "Glarus", "canton": "GL", "cantonId": 8, "income": 25000.0, "values": [0.0, 0.0, 0.0]}, {"bfsId": 1632, "municipality": "Glarus", "canton": "GL", "cantonId": 8, "income": 30000.0, "values": [0.0, 0.0, 0.0]}, {"bfsId": 1632, "municipality": "Glarus", "canton": "GL", "cantonId": 8, "income": 35000.0, "values": [362.0, 287.0, 281.0]}, {"bfsId": 1632, "municipality": "Glarus", "canton": "GL", "cantonId": 8, "income": 40000.0, "values": [772.0, 696.0, 682.0]}, {"bfsId": 1632, "municipality": "Glarus", "canton": "GL", "cantonId": 8, "income": 45000.0, "values": [1203.0, 1115.0, 1093.0]}, {"bfsId": 1632, "municipality": "Glarus", "canton": "GL", "cantonId": 8, "income": 50000.0, "values": [1653.0, 1531.0, 1501.0]}, {"bfsId": 1632, "municipality": "Glarus", "canton": "GL", "cantonId": 8, "income": 60000.0, "values": [2792.0, 2671.0, 2619.0]}, {"bfsId": 1632, "municipality": "Glarus", "canton": "GL", "cantonId": 8, "income": 70000.0, "values": [4014.0, 3872.0, 3777.0]}, {"bfsId": 1632, "municipality": "Glarus", "canton": "GL", "cantonId": 8, "income": 80000.0, "values": [5516.0, 5383.0, 5281.0]}, {"bfsId": 1632, "municipality": "Glarus", "canton": "GL", "cantonId": 8, "income": 90000.0, "values": [7113.0, 6957.0, 6830.0]}, {"bfsId": 1632, "municipality": "Glarus", "canton": "GL", "cantonId": 8, "income": 100000.0, "values": [8729.0, 8571.0, 8417.0]}, {"bfsId": 1632, "municipality": "Glarus", "canton": "GL", "cantonId": 8, "income": 125000.0, "values": [13465.0, 13281.0, 13055.0]}, {"bfsId": 1632, "municipality": "Glarus", "canton": "GL", "cantonId": 8, "income": 150000.0, "values": [18659.0, 18463.0, 18162.0]}, {"bfsId": 1632, "municipality": "Glarus", "canton": "GL", "cantonId": 8, "income": 175000.0, "values": [24726.0, 24495.0, 24115.0]}, {"bfsId": 1632, "municipality": "Glarus", "canton": "GL", "cantonId": 8, "income": 200000.0, "values": [31745.0, 31497.0, 31011.0]}, {"bfsId": 1632, "municipality": "Glarus", "canton": "GL", "cantonId": 8, "income": 250000.0, "values": [46183.0, 45903.0, 45277.0]}, {"bfsId": 1632, "municipality": "Glarus", "canton": "GL", "cantonId": 8, "income": 300000.0, "values": [60948.0, 60616.0, 59781.0]}, {"bfsId": 1632, "municipality": "Glarus", "canton": "GL", "cantonId": 8, "income": 400000.0, "values": [91427.0, 91058.0, 89860.0]}, {"bfsId": 1632, "municipality": "Glarus", "canton": "GL", "cantonId": 8, "income": 500000.0, "values": [122614.0, 122184.0, 120573.0]}, {"bfsId": 1632, "municipality": "Glarus", "canton": "GL", "cantonId": 8, "income": 750000.0, "values": [203478.0, 202865.0, 200248.0]}, {"bfsId": 1632, "municipality": "Glarus", "canton": "GL", "cantonId": 8, "income": 1000000.0, "values": [280946.0, 280292.0, 276711.0]}, {"bfsId": 1632, "municipality": "Glarus", "canton": "GL", "cantonId": 8, "income": 5000000.0, "values": [1425087.0, 1422566.0, 1404490.0]}, {"bfsId": 1632, "municipality": "Glarus", "canton": "GL", "cantonId": 8, "income": 10000000.0, "values": [2855216.0, 2850335.0, 2814150.0]}, {"bfsId": 1632, "municipality": "Glarus", "canton": "GL", "cantonId": 8, "income": 50000000.0, "values": [14296379.0, 14272613.0, 14091425.0]}, {"bfsId": 1632, "municipality": "Glarus", "canton": "GL", "cantonId": 8, "income": 100000000.0, "values": [28597832.0, 28550460.0, 28188019.0]}, {"bfsId": 1711, "municipality": "Zug", "canton": "ZG", "cantonId": 9, "income": 15000.0, "values": [0.0, 0.0, 0.0]}, {"bfsId": 1711, "municipality": "Zug", "canton": "ZG", "cantonId": 9, "income": 20000.0, "values": [0.0, 0.0, 0.0]}, {"bfsId": 1711, "municipality": "Zug", "canton": "ZG", "cantonId": 9, "income": 25000.0, "values": [0.0, 0.0, 0.0]}, {"bfsId": 1711, "municipality": "Zug", "canton": "ZG", "cantonId": 9, "income": 30000.0, "values": [0.0, 0.0, 0.0]}, {"bfsId": 1711, "municipality": "Zug", "canton": "ZG", "cantonId": 9, "income": 35000.0, "values": [0.0, 0.0, 0.0]}, {"bfsId": 1711, "municipality": "Zug", "canton": "ZG", "cantonId": 9, "income": 40000.0, "values": [0.0, 0.0, 0.0]}, {"bfsId": 1711, "municipality": "Zug", "canton": "ZG", "cantonId": 9, "income": 45000.0, "values": [0.0, 0.0, 0.0]}, {"bfsId": 1711, "municipality": "Zug", "canton": "ZG", "cantonId": 9, "income": 50000.0, "values": [23.0, 22.0, 0.0]}, {"bfsId": 1711, "municipality": "Zug", "canton": "ZG", "cantonId": 9, "income": 60000.0, "values": [211.0, 208.0, 32.0]}, {"bfsId": 1711, "municipality": "Zug", "canton": "ZG", "cantonId": 9, "income": 70000.0, "values": [572.0, 567.0, 208.0]}, {"bfsId": 1711, "municipality": "Zug", "canton": "ZG", "cantonId": 9, "income": 80000.0, "values": [1149.0, 1142.0, 718.0]}, {"bfsId": 1711, "municipality": "Zug", "canton": "ZG", "cantonId": 9, "income": 90000.0, "values": [1820.0, 1809.0, 1325.0]}, {"bfsId": 1711, "municipality": "Zug", "canton": "ZG", "cantonId": 9, "income": 100000.0, "values": [2571.0, 2553.0, 1983.0]}, {"bfsId": 1711, "municipality": "Zug", "canton": "ZG", "cantonId": 9, "income": 125000.0, "values": [4868.0, 4843.0, 4027.0]}, {"bfsId": 1711, "municipality": "Zug", "canton": "ZG", "cantonId": 9, "income": 150000.0, "values": [7844.0, 7815.0, 6713.0]}, {"bfsId": 1711, "municipality": "Zug", "canton": "ZG", "cantonId": 9, "income": 175000.0, "values": [11600.0, 11542.0, 10415.0]}, {"bfsId": 1711, "municipality": "Zug", "canton": "ZG", "cantonId": 9, "income": 200000.0, "values": [17000.0, 16929.0, 15273.0]}, {"bfsId": 1711, "municipality": "Zug", "canton": "ZG", "cantonId": 9, "income": 250000.0, "values": [30350.0, 30234.0, 27205.0]}, {"bfsId": 1711, "municipality": "Zug", "canton": "ZG", "cantonId": 9, "income": 300000.0, "values": [43476.0, 43343.0, 40182.0]}, {"bfsId": 1711, "municipality": "Zug", "canton": "ZG", "cantonId": 9, "income": 400000.0, "values": [66636.0, 66493.0, 64027.0]}, {"bfsId": 1711, "municipality": "Zug", "canton": "ZG", "cantonId": 9, "income": 500000.0, "values": [88343.0, 88176.0, 85541.0]}, {"bfsId": 1711, "municipality": "Zug", "canton": "ZG", "cantonId": 9, "income": 750000.0, "values": [142598.0, 142336.0, 139338.0]}, {"bfsId": 1711, "municipality": "Zug", "canton": "ZG", "cantonId": 9, "income": 1000000.0, "values": [196854.0, 196496.0, 193111.0]}, {"bfsId": 1711, "municipality": "Zug", "canton": "ZG", "cantonId": 9, "income": 5000000.0, "values": [1010391.0, 1008712.0, 999304.0]}, {"bfsId": 1711, "municipality": "Zug", "canton": "ZG", "cantonId": 9, "income": 10000000.0, "values": [2027270.0, 2023913.0, 2006981.0]}, {"bfsId": 1711, "municipality": "Zug", "canton": "ZG", "cantonId": 9, "income": 50000000.0, "values": [10162400.0, 10145615.0, 10068397.0]}, {"bfsId": 1711, "municipality": "Zug", "canton": "ZG", "cantonId": 9, "income": 100000000.0, "values": [20331313.0, 20297743.0, 20145167.0]}, {"bfsId": 2196, "municipality": "Fribourg", "canton": "FR", "cantonId": 10, "income": 15000.0, "values": [91.0, 90.0, 89.0]}, {"bfsId": 2196, "municipality": "Fribourg", "canton": "FR", "cantonId": 10, "income": 20000.0, "values": [91.0, 90.0, 89.0]}, {"bfsId": 2196, "municipality": "Fribourg", "canton": "FR", "cantonId": 10, "income": 25000.0, "values": [91.0, 90.0, 89.0]}, {"bfsId": 2196, "municipality": "Fribourg", "canton": "FR", "cantonId": 10, "income": 30000.0, "values": [123.0, 121.0, 114.0]}, {"bfsId": 2196, "municipality": "Fribourg", "canton": "FR", "cantonId": 10, "income": 35000.0, "values": [240.0, 237.0, 216.0]}, {"bfsId": 2196, "municipality": "Fribourg", "canton": "FR", "cantonId": 10, "income": 40000.0, "values": [567.0, 562.0, 514.0]}, {"bfsId": 2196, "municipality": "Fribourg", "canton": "FR", "cantonId": 10, "income": 45000.0, "values": [1013.0, 1004.0, 954.0]}, {"bfsId": 2196, "municipality": "Fribourg", "canton": "FR", "cantonId": 10, "income": 50000.0, "values": [1616.0, 1572.0, 1507.0]}, {"bfsId": 2196, "municipality": "Fribourg", "canton": "FR", "cantonId": 10, "income": 60000.0, "values": [3036.0, 3001.0, 2924.0]}, {"bfsId": 2196, "municipality": "Fribourg", "canton": "FR", "cantonId": 10, "income": 70000.0, "values": [4358.0, 4311.0, 4210.0]}, {"bfsId": 2196, "municipality": "Fribourg", "canton": "FR", "cantonId": 10, "income": 80000.0, "values": [6070.0, 6004.0, 5870.0]}, {"bfsId": 2196, "municipality": "Fribourg", "canton": "FR", "cantonId": 10, "income": 90000.0, "values": [8103.0, 7983.0, 7839.0]}, {"bfsId": 2196, "municipality": "Fribourg", "canton": "FR", "cantonId": 10, "income": 100000.0, "values": [10111.0, 9981.0, 9827.0]}, {"bfsId": 2196, "municipality": "Fribourg", "canton": "FR", "cantonId": 10, "income": 125000.0, "values": [15873.0, 15697.0, 15460.0]}, {"bfsId": 2196, "municipality": "Fribourg", "canton": "FR", "cantonId": 10, "income": 150000.0, "values": [22030.0, 21804.0, 21503.0]}, {"bfsId": 2196, "municipality": "Fribourg", "canton": "FR", "cantonId": 10, "income": 175000.0, "values": [29655.0, 29352.0, 28981.0]}, {"bfsId": 2196, "municipality": "Fribourg", "canton": "FR", "cantonId": 10, "income": 200000.0, "values": [38322.0, 37940.0, 37501.0]}, {"bfsId": 2196, "municipality": "Fribourg", "canton": "FR", "cantonId": 10, "income": 250000.0, "values": [55672.0, 55150.0, 54588.0]}, {"bfsId": 2196, "municipality": "Fribourg", "canton": "FR", "cantonId": 10, "income": 300000.0, "values": [74101.0, 73445.0, 72723.0]}, {"bfsId": 2196, "municipality": "Fribourg", "canton": "FR", "cantonId": 10, "income": 400000.0, "values": [112989.0, 112012.0, 110985.0]}, {"bfsId": 2196, "municipality": "Fribourg", "canton": "FR", "cantonId": 10, "income": 500000.0, "values": [150486.0, 149258.0, 147960.0]}, {"bfsId": 2196, "municipality": "Fribourg", "canton": "FR", "cantonId": 10, "income": 750000.0, "values": [235722.0, 233854.0, 231919.0]}, {"bfsId": 2196, "municipality": "Fribourg", "canton": "FR", "cantonId": 10, "income": 1000000.0, "values": [320959.0, 318475.0, 315891.0]}, {"bfsId": 2196, "municipality": "Fribourg", "canton": "FR", "cantonId": 10, "income": 5000000.0, "values": [1630164.0, 1617703.0, 1604970.0]}, {"bfsId": 2196, "municipality": "Fribourg", "canton": "FR", "cantonId": 10, "income": 10000000.0, "values": [3266623.0, 3241663.0, 3216256.0]}, {"bfsId": 2196, "municipality": "Fribourg", "canton": "FR", "cantonId": 10, "income": 50000000.0, "values": [16358439.0, 16233483.0, 16106540.0]}, {"bfsId": 2196, "municipality": "Fribourg", "canton": "FR", "cantonId": 10, "income": 100000000.0, "values": [32723209.0, 32473258.0, 32219395.0]}, {"bfsId": 2601, "municipality": "Solothurn", "canton": "SO", "cantonId": 11, "income": 15000.0, "values": [50.0, 50.0, 50.0]}, {"bfsId": 2601, "municipality": "Solothurn", "canton": "SO", "cantonId": 11, "income": 20000.0, "values": [50.0, 50.0, 50.0]}, {"bfsId": 2601, "municipality": "Solothurn", "canton": "SO", "cantonId": 11, "income": 25000.0, "values": [50.0, 50.0, 50.0]}, {"bfsId": 2601, "municipality": "Solothurn", "canton": "SO", "cantonId": 11, "income": 30000.0, "values": [50.0, 50.0, 50.0]}, {"bfsId": 2601, "municipality": "Solothurn", "canton": "SO", "cantonId": 11, "income": 35000.0, "values": [266.0, 50.0, 50.0]}, {"bfsId": 2601, "municipality": "Solothurn", "canton": "SO", "cantonId": 11, "income": 40000.0, "values": [756.0, 322.0, 322.0]}, {"bfsId": 2601, "municipality": "Solothurn", "canton": "SO", "cantonId": 11, "income": 45000.0, "values": [1323.0, 855.0, 855.0]}, {"bfsId": 2601, "municipality": "Solothurn", "canton": "SO", "cantonId": 11, "income": 50000.0, "values": [1933.0, 1454.0, 1454.0]}, {"bfsId": 2601, "municipality": "Solothurn", "canton": "SO", "cantonId": 11, "income": 60000.0, "values": [3256.0, 2864.0, 2862.0]}, {"bfsId": 2601, "municipality": "Solothurn", "canton": "SO", "cantonId": 11, "income": 70000.0, "values": [4717.0, 4444.0, 4443.0]}, {"bfsId": 2601, "municipality": "Solothurn", "canton": "SO", "cantonId": 11, "income": 80000.0, "values": [6477.0, 6284.0, 6282.0]}, {"bfsId": 2601, "municipality": "Solothurn", "canton": "SO", "cantonId": 11, "income": 90000.0, "values": [8412.0, 8268.0, 8264.0]}, {"bfsId": 2601, "municipality": "Solothurn", "canton": "SO", "cantonId": 11, "income": 100000.0, "values": [10474.0, 10301.0, 10297.0]}, {"bfsId": 2601, "municipality": "Solothurn", "canton": "SO", "cantonId": 11, "income": 125000.0, "values": [15925.0, 15679.0, 15671.0]}, {"bfsId": 2601, "municipality": "Solothurn", "canton": "SO", "cantonId": 11, "income": 150000.0, "values": [21947.0, 21621.0, 21613.0]}, {"bfsId": 2601, "municipality": "Solothurn", "canton": "SO", "cantonId": 11, "income": 175000.0, "values": [28981.0, 28554.0, 28544.0]}, {"bfsId": 2601, "municipality": "Solothurn", "canton": "SO", "cantonId": 11, "income": 200000.0, "values": [37033.0, 36522.0, 36498.0]}, {"bfsId": 2601, "municipality": "Solothurn", "canton": "SO", "cantonId": 11, "income": 250000.0, "values": [53709.0, 53009.0, 52993.0]}, {"bfsId": 2601, "municipality": "Solothurn", "canton": "SO", "cantonId": 11, "income": 300000.0, "values": [70806.0, 69918.0, 69887.0]}, {"bfsId": 2601, "municipality": "Solothurn", "canton": "SO", "cantonId": 11, "income": 400000.0, "values": [104974.0, 103724.0, 103686.0]}, {"bfsId": 2601, "municipality": "Solothurn", "canton": "SO", "cantonId": 11, "income": 500000.0, "values": [139155.0, 137542.0, 137486.0]}, {"bfsId": 2601, "municipality": "Solothurn", "canton": "SO", "cantonId": 11, "income": 750000.0, "values": [222935.0, 220442.0, 220375.0]}, {"bfsId": 2601, "municipality": "Solothurn", "canton": "SO", "cantonId": 11, "income": 1000000.0, "values": [303520.0, 300177.0, 300083.0]}, {"bfsId": 2601, "municipality": "Solothurn", "canton": "SO", "cantonId": 11, "income": 5000000.0, "values": [1538354.0, 1521563.0, 1521136.0]}, {"bfsId": 2601, "municipality": "Solothurn", "canton": "SO", "cantonId": 11, "income": 10000000.0, "values": [3081859.0, 3048231.0, 3047391.0]}, {"bfsId": 2601, "municipality": "Solothurn", "canton": "SO", "cantonId": 11, "income": 50000000.0, "values": [15429954.0, 15261631.0, 15257425.0]}, {"bfsId": 2601, "municipality": "Solothurn", "canton": "SO", "cantonId": 11, "income": 100000000.0, "values": [30865073.0, 30528381.0, 30519967.0]}, {"bfsId": 2701, "municipality": "Basel", "canton": "BS", "cantonId": 12, "income": 15000.0, "values": [0.0, 0.0, 0.0]}, {"bfsId": 2701, "municipality": "Basel", "canton": "BS", "cantonId": 12, "income": 20000.0, "values": [0.0, 0.0, 0.0]}, {"bfsId": 2701, "municipality": "Basel", "canton": "BS", "cantonId": 12, "income": 25000.0, "values": [0.0, 0.0, 0.0]}, {"bfsId": 2701, "municipality": "Basel", "canton": "BS", "cantonId": 12, "income": 30000.0, "values": [0.0, 0.0, 0.0]}, {"bfsId": 2701, "municipality": "Basel", "canton": "BS", "cantonId": 12, "income": 35000.0, "values": [0.0, 0.0, 0.0]}, {"bfsId": 2701, "municipality": "Basel", "canton": "BS", "cantonId": 12, "income": 40000.0, "values": [0.0, 0.0, 0.0]}, {"bfsId": 2701, "municipality": "Basel", "canton": "BS", "cantonId": 12, "income": 45000.0, "values": [0.0, 0.0, 0.0]}, {"bfsId": 2701, "municipality": "Basel", "canton": "BS", "cantonId": 12, "income": 50000.0, "values": [264.0, 88.0, 88.0]}, {"bfsId": 2701, "municipality": "Basel", "canton": "BS", "cantonId": 12, "income": 60000.0, "values": [2200.0, 2002.0, 2002.0]}, {"bfsId": 2701, "municipality": "Basel", "canton": "BS", "cantonId": 12, "income": 70000.0, "values": [4158.0, 3936.0, 3916.0]}, {"bfsId": 2701, "municipality": "Basel", "canton": "BS", "cantonId": 12, "income": 80000.0, "values": [6291.0, 6044.0, 6044.0]}, {"bfsId": 2701, "municipality": "Basel", "canton": "BS", "cantonId": 12, "income": 90000.0, "values": [8510.0, 8238.0, 8216.0]}, {"bfsId": 2701, "municipality": "Basel", "canton": "BS", "cantonId": 12, "income": 100000.0, "values": [10780.0, 10462.0, 10462.0]}, {"bfsId": 2701, "municipality": "Basel", "canton": "BS", "cantonId": 12, "income": 125000.0, "values": [16699.0, 16323.0, 16301.0]}, {"bfsId": 2701, "municipality": "Basel", "canton": "BS", "cantonId": 12, "income": 150000.0, "values": [22972.0, 22536.0, 22536.0]}, {"bfsId": 2701, "municipality": "Basel", "canton": "BS", "cantonId": 12, "income": 175000.0, "values": [30039.0, 29503.0, 29503.0]}, {"bfsId": 2701, "municipality": "Basel", "canton": "BS", "cantonId": 12, "income": 200000.0, "values": [37980.0, 37383.0, 37348.0]}, {"bfsId": 2701, "municipality": "Basel", "canton": "BS", "cantonId": 12, "income": 250000.0, "values": [53870.0, 53126.0, 53126.0]}, {"bfsId": 2701, "municipality": "Basel", "canton": "BS", "cantonId": 12, "income": 300000.0, "values": [69795.0, 68902.0, 68867.0]}, {"bfsId": 2701, "municipality": "Basel", "canton": "BS", "cantonId": 12, "income": 400000.0, "values": [101575.0, 100421.0, 100386.0]}, {"bfsId": 2701, "municipality": "Basel", "canton": "BS", "cantonId": 12, "income": 500000.0, "values": [133734.0, 132229.0, 132147.0]}, {"bfsId": 2701, "municipality": "Basel", "canton": "BS", "cantonId": 12, "income": 750000.0, "values": [222342.0, 225557.0, 225473.0]}, {"bfsId": 2701, "municipality": "Basel", "canton": "BS", "cantonId": 12, "income": 1000000.0, "values": [310950.0, 320813.0, 320688.0]}, {"bfsId": 2701, "municipality": "Basel", "canton": "BS", "cantonId": 12, "income": 5000000.0, "values": [1674099.0, 1790604.0, 1790079.0]}, {"bfsId": 2701, "municipality": "Basel", "canton": "BS", "cantonId": 12, "income": 10000000.0, "values": [3377986.0, 3627765.0, 3626754.0]}, {"bfsId": 2701, "municipality": "Basel", "canton": "BS", "cantonId": 12, "income": 50000000.0, "values": [17009236.0, 18325215.0, 18320154.0]}, {"bfsId": 2701, "municipality": "Basel", "canton": "BS", "cantonId": 12, "income": 100000000.0, "values": [34048299.0, 36697029.0, 36686904.0]}, {"bfsId": 2829, "municipality": "Liestal", "canton": "BL", "cantonId": 13, "income": 15000.0, "values": [0.0, 0.0, 0.0]}, {"bfsId": 2829, "municipality": "Liestal", "canton": "BL", "cantonId": 13, "income": 20000.0, "values": [0.0, 0.0, 0.0]}, {"bfsId": 2829, "municipality": "Liestal", "canton": "BL", "cantonId": 13, "income": 25000.0, "values": [0.0, 0.0, 0.0]}, {"bfsId": 2829, "municipality": "Liestal", "canton": "BL", "cantonId": 13, "income": 30000.0, "values": [0.0, 0.0, 0.0]}, {"bfsId": 2829, "municipality": "Liestal", "canton": "BL", "cantonId": 13, "income": 35000.0, "values": [0.0, 0.0, 0.0]}, {"bfsId": 2829, "municipality": "Liestal", "canton": "BL", "cantonId": 13, "income": 40000.0, "values": [0.0, 0.0, 0.0]}, {"bfsId": 2829, "municipality": "Liestal", "canton": "BL", "cantonId": 13, "income": 45000.0, "values": [0.0, 0.0, 0.0]}, {"bfsId": 2829, "municipality": "Liestal", "canton": "BL", "cantonId": 13, "income": 50000.0, "values": [54.0, 45.0, 45.0]}, {"bfsId": 2829, "municipality": "Liestal", "canton": "BL", "cantonId": 13, "income": 60000.0, "values": [1218.0, 1204.0, 1203.0]}, {"bfsId": 2829, "municipality": "Liestal", "canton": "BL", "cantonId": 13, "income": 70000.0, "values": [2607.0, 2589.0, 2588.0]}, {"bfsId": 2829, "municipality": "Liestal", "canton": "BL", "cantonId": 13, "income": 80000.0, "values": [4386.0, 4360.0, 4359.0]}, {"bfsId": 2829, "municipality": "Liestal", "canton": "BL", "cantonId": 13, "income": 90000.0, "values": [6412.0, 6377.0, 6374.0]}, {"bfsId": 2829, "municipality": "Liestal", "canton": "BL", "cantonId": 13, "income": 100000.0, "values": [8634.0, 8593.0, 8587.0]}, {"bfsId": 2829, "municipality": "Liestal", "canton": "BL", "cantonId": 13, "income": 125000.0, "values": [14764.0, 14709.0, 14702.0]}, {"bfsId": 2829, "municipality": "Liestal", "canton": "BL", "cantonId": 13, "income": 150000.0, "values": [21605.0, 21535.0, 21525.0]}, {"bfsId": 2829, "municipality": "Liestal", "canton": "BL", "cantonId": 13, "income": 175000.0, "values": [29487.0, 29383.0, 29371.0]}, {"bfsId": 2829, "municipality": "Liestal", "canton": "BL", "cantonId": 13, "income": 200000.0, "values": [38504.0, 38383.0, 38357.0]}, {"bfsId": 2829, "municipality": "Liestal", "canton": "BL", "cantonId": 13, "income": 250000.0, "values": [57130.0, 56970.0, 56953.0]}, {"bfsId": 2829, "municipality": "Liestal", "canton": "BL", "cantonId": 13, "income": 300000.0, "values": [76091.0, 75897.0, 75861.0]}, {"bfsId": 2829, "municipality": "Liestal", "canton": "BL", "cantonId": 13, "income": 400000.0, "values": [114369.0, 114115.0, 114072.0]}, {"bfsId": 2829, "municipality": "Liestal", "canton": "BL", "cantonId": 13, "income": 500000.0, "values": [153060.0, 152746.0, 152682.0]}, {"bfsId": 2829, "municipality": "Liestal", "canton": "BL", "cantonId": 13, "income": 750000.0, "values": [251059.0, 250574.0, 250491.0]}, {"bfsId": 2829, "municipality": "Liestal", "canton": "BL", "cantonId": 13, "income": 1000000.0, "values": [350398.0, 349740.0, 349623.0]}, {"bfsId": 2829, "municipality": "Liestal", "canton": "BL", "cantonId": 13, "income": 5000000.0, "values": [1904113.0, 1900945.0, 1900413.0]}, {"bfsId": 2829, "municipality": "Liestal", "canton": "BL", "cantonId": 13, "income": 10000000.0, "values": [3822614.0, 3816280.0, 3815226.0]}, {"bfsId": 2829, "municipality": "Liestal", "canton": "BL", "cantonId": 13, "income": 50000000.0, "values": [19170674.0, 19139007.0, 19133730.0]}, {"bfsId": 2829, "municipality": "Liestal", "canton": "BL", "cantonId": 13, "income": 100000000.0, "values": [38355751.0, 38292416.0, 38281861.0]}, {"bfsId": 2939, "municipality": "Schaffhausen", "canton": "SH", "cantonId": 14, "income": 15000.0, "values": [60.0, 60.0, 60.0]}, {"bfsId": 2939, "municipality": "Schaffhausen", "canton": "SH", "cantonId": 14, "income": 20000.0, "values": [60.0, 60.0, 60.0]}, {"bfsId": 2939, "municipality": "Schaffhausen", "canton": "SH", "cantonId": 14, "income": 25000.0, "values": [60.0, 60.0, 60.0]}, {"bfsId": 2939, "municipality": "Schaffhausen", "canton": "SH", "cantonId": 14, "income": 30000.0, "values": [60.0, 60.0, 60.0]}, {"bfsId": 2939, "municipality": "Schaffhausen", "canton": "SH", "cantonId": 14, "income": 35000.0, "values": [195.0, 163.0, 60.0]}, {"bfsId": 2939, "municipality": "Schaffhausen", "canton": "SH", "cantonId": 14, "income": 40000.0, "values": [509.0, 439.0, 255.0]}, {"bfsId": 2939, "municipality": "Schaffhausen", "canton": "SH", "cantonId": 14, "income": 45000.0, "values": [957.0, 858.0, 595.0]}, {"bfsId": 2939, "municipality": "Schaffhausen", "canton": "SH", "cantonId": 14, "income": 50000.0, "values": [1457.0, 1335.0, 1031.0]}, {"bfsId": 2939, "municipality": "Schaffhausen", "canton": "SH", "cantonId": 14, "income": 60000.0, "values": [2488.0, 2323.0, 1995.0]}, {"bfsId": 2939, "municipality": "Schaffhausen", "canton": "SH", "cantonId": 14, "income": 70000.0, "values": [3701.0, 3517.0, 3105.0]}, {"bfsId": 2939, "municipality": "Schaffhausen", "canton": "SH", "cantonId": 14, "income": 80000.0, "values": [5107.0, 4885.0, 4402.0]}, {"bfsId": 2939, "municipality": "Schaffhausen", "canton": "SH", "cantonId": 14, "income": 90000.0, "values": [6597.0, 6333.0, 5832.0]}, {"bfsId": 2939, "municipality": "Schaffhausen", "canton": "SH", "cantonId": 14, "income": 100000.0, "values": [8281.0, 7964.0, 7386.0]}, {"bfsId": 2939, "municipality": "Schaffhausen", "canton": "SH", "cantonId": 14, "income": 125000.0, "values": [13088.0, 12659.0, 11966.0]}, {"bfsId": 2939, "municipality": "Schaffhausen", "canton": "SH", "cantonId": 14, "income": 150000.0, "values": [18670.0, 18118.0, 17303.0]}, {"bfsId": 2939, "municipality": "Schaffhausen", "canton": "SH", "cantonId": 14, "income": 175000.0, "values": [25578.0, 24839.0, 23895.0]}, {"bfsId": 2939, "municipality": "Schaffhausen", "canton": "SH", "cantonId": 14, "income": 200000.0, "values": [33589.0, 32723.0, 31675.0]}, {"bfsId": 2939, "municipality": "Schaffhausen", "canton": "SH", "cantonId": 14, "income": 250000.0, "values": [49630.0, 48486.0, 47317.0]}, {"bfsId": 2939, "municipality": "Schaffhausen", "canton": "SH", "cantonId": 14, "income": 300000.0, "values": [65712.0, 64278.0, 62929.0]}, {"bfsId": 2939, "municipality": "Schaffhausen", "canton": "SH", "cantonId": 14, "income": 400000.0, "values": [99412.0, 97376.0, 95645.0]}, {"bfsId": 2939, "municipality": "Schaffhausen", "canton": "SH", "cantonId": 14, "income": 500000.0, "values": [131704.0, 129186.0, 127244.0]}, {"bfsId": 2939, "municipality": "Schaffhausen", "canton": "SH", "cantonId": 14, "income": 750000.0, "values": [206900.0, 203128.0, 200512.0]}, {"bfsId": 2939, "municipality": "Schaffhausen", "canton": "SH", "cantonId": 14, "income": 1000000.0, "values": [282097.0, 277069.0, 273747.0]}, {"bfsId": 2939, "municipality": "Schaffhausen", "canton": "SH", "cantonId": 14, "income": 5000000.0, "values": [1430671.0, 1405807.0, 1391403.0]}, {"bfsId": 2939, "municipality": "Schaffhausen", "canton": "SH", "cantonId": 14, "income": 10000000.0, "values": [2866343.0, 2816656.0, 2788411.0]}, {"bfsId": 2939, "municipality": "Schaffhausen", "canton": "SH", "cantonId": 14, "income": 50000000.0, "values": [14351853.0, 14103571.0, 13964464.0]}, {"bfsId": 2939, "municipality": "Schaffhausen", "canton": "SH", "cantonId": 14, "income": 100000000.0, "values": [28708741.0, 28212217.0, 27934532.0]}, {"bfsId": 3001, "municipality": "Herisau", "canton": "AR", "cantonId": 15, "income": 15000.0, "values": [0.0, 0.0, 0.0]}, {"bfsId": 3001, "municipality": "Herisau", "canton": "AR", "cantonId": 15, "income": 20000.0, "values": [0.0, 0.0, 0.0]}, {"bfsId": 3001, "municipality": "Herisau", "canton": "AR", "cantonId": 15, "income": 25000.0, "values": [0.0, 0.0, 0.0]}, {"bfsId": 3001, "municipality": "Herisau", "canton": "AR", "cantonId": 15, "income": 30000.0, "values": [48.0, 48.0, 48.0]}, {"bfsId": 3001, "municipality": "Herisau", "canton": "AR", "cantonId": 15, "income": 35000.0, "values": [346.0, 346.0, 346.0]}, {"bfsId": 3001, "municipality": "Herisau", "canton": "AR", "cantonId": 15, "income": 40000.0, "values": [805.0, 805.0, 805.0]}, {"bfsId": 3001, "municipality": "Herisau", "canton": "AR", "cantonId": 15, "income": 45000.0, "values": [1370.0, 1358.0, 1358.0]}, {"bfsId": 3001, "municipality": "Herisau", "canton": "AR", "cantonId": 15, "income": 50000.0, "values": [1924.0, 1911.0, 1911.0]}, {"bfsId": 3001, "municipality": "Herisau", "canton": "AR", "cantonId": 15, "income": 60000.0, "values": [3162.0, 3147.0, 3147.0]}, {"bfsId": 3001, "municipality": "Herisau", "canton": "AR", "cantonId": 15, "income": 70000.0, "values": [4473.0, 4456.0, 4440.0]}, {"bfsId": 3001, "municipality": "Herisau", "canton": "AR", "cantonId": 15, "income": 80000.0, "values": [6102.0, 6083.0, 6083.0]}, {"bfsId": 3001, "municipality": "Herisau", "canton": "AR", "cantonId": 15, "income": 90000.0, "values": [7932.0, 7908.0, 7890.0]}, {"bfsId": 3001, "municipality": "Herisau", "canton": "AR", "cantonId": 15, "income": 100000.0, "values": [9888.0, 9842.0, 9842.0]}, {"bfsId": 3001, "municipality": "Herisau", "canton": "AR", "cantonId": 15, "income": 125000.0, "values": [15268.0, 15218.0, 15199.0]}, {"bfsId": 3001, "municipality": "Herisau", "canton": "AR", "cantonId": 15, "income": 150000.0, "values": [21195.0, 21140.0, 21140.0]}, {"bfsId": 3001, "municipality": "Herisau", "canton": "AR", "cantonId": 15, "income": 175000.0, "values": [27970.0, 27872.0, 27872.0]}, {"bfsId": 3001, "municipality": "Herisau", "canton": "AR", "cantonId": 15, "income": 200000.0, "values": [35621.0, 35520.0, 35486.0]}, {"bfsId": 3001, "municipality": "Herisau", "canton": "AR", "cantonId": 15, "income": 250000.0, "values": [51264.0, 51126.0, 51126.0]}, {"bfsId": 3001, "municipality": "Herisau", "canton": "AR", "cantonId": 15, "income": 300000.0, "values": [66943.0, 66771.0, 66737.0]}, {"bfsId": 3001, "municipality": "Herisau", "canton": "AR", "cantonId": 15, "income": 400000.0, "values": [98233.0, 98026.0, 97992.0]}, {"bfsId": 3001, "municipality": "Herisau", "canton": "AR", "cantonId": 15, "income": 500000.0, "values": [128616.0, 128390.0, 128326.0]}, {"bfsId": 3001, "municipality": "Herisau", "canton": "AR", "cantonId": 15, "income": 750000.0, "values": [201865.0, 201510.0, 201446.0]}, {"bfsId": 3001, "municipality": "Herisau", "canton": "AR", "cantonId": 15, "income": 1000000.0, "values": [275114.0, 274631.0, 274534.0]}, {"bfsId": 3001, "municipality": "Herisau", "canton": "AR", "cantonId": 15, "income": 5000000.0, "values": [1392537.0, 1390231.0, 1389832.0]}, {"bfsId": 3001, "municipality": "Herisau", "canton": "AR", "cantonId": 15, "income": 10000000.0, "values": [2789270.0, 2784659.0, 2783891.0]}, {"bfsId": 3001, "municipality": "Herisau", "canton": "AR", "cantonId": 15, "income": 50000000.0, "values": [13963260.0, 13940205.0, 13936363.0]}, {"bfsId": 3001, "municipality": "Herisau", "canton": "AR", "cantonId": 15, "income": 100000000.0, "values": [27930748.0, 27884638.0, 27876953.0]}, {"bfsId": 3101, "municipality": "Appenzell", "canton": "AI", "cantonId": 16, "income": 15000.0, "values": [0.0, 0.0, 0.0]}, {"bfsId": 3101, "municipality": "Appenzell", "canton": "AI", "cantonId": 16, "income": 20000.0, "values": [10.0, 10.0, 10.0]}, {"bfsId": 3101, "municipality": "Appenzell", "canton": "AI", "cantonId": 16, "income": 25000.0, "values": [87.0, 85.0, 83.0]}, {"bfsId": 3101, "municipality": "Appenzell", "canton": "AI", "cantonId": 16, "income": 30000.0, "values": [219.0, 215.0, 210.0]}, {"bfsId": 3101, "municipality": "Appenzell", "canton": "AI", "cantonId": 16, "income": 35000.0, "values": [386.0, 379.0, 369.0]}, {"bfsId": 3101, "municipality": "Appenzell", "canton": "AI", "cantonId": 16, "income": 40000.0, "values": [592.0, 581.0, 566.0]}, {"bfsId": 3101, "municipality": "Appenzell", "canton": "AI", "cantonId": 16, "income": 45000.0, "values": [863.0, 838.0, 816.0]}, {"bfsId": 3101, "municipality": "Appenzell", "canton": "AI", "cantonId": 16, "income": 50000.0, "values": [1176.0, 1141.0, 1112.0]}, {"bfsId": 3101, "municipality": "Appenzell", "canton": "AI", "cantonId": 16, "income": 60000.0, "values": [1932.0, 1881.0, 1834.0]}, {"bfsId": 3101, "municipality": "Appenzell", "canton": "AI", "cantonId": 16, "income": 70000.0, "values": [2831.0, 2761.0, 2692.0]}, {"bfsId": 3101, "municipality": "Appenzell", "canton": "AI", "cantonId": 16, "income": 80000.0, "values": [4021.0, 3930.0, 3835.0]}, {"bfsId": 3101, "municipality": "Appenzell", "canton": "AI", "cantonId": 16, "income": 90000.0, "values": [5353.0, 5249.0, 5110.0]}, {"bfsId": 3101, "municipality": "Appenzell", "canton": "AI", "cantonId": 16, "income": 100000.0, "values": [6804.0, 6657.0, 6507.0]}, {"bfsId": 3101, "municipality": "Appenzell", "canton": "AI", "cantonId": 16, "income": 125000.0, "values": [10818.0, 10612.0, 10369.0]}, {"bfsId": 3101, "municipality": "Appenzell", "canton": "AI", "cantonId": 16, "income": 150000.0, "values": [15229.0, 14961.0, 14659.0]}, {"bfsId": 3101, "municipality": "Appenzell", "canton": "AI", "cantonId": 16, "income": 175000.0, "values": [20400.0, 20036.0, 19657.0]}, {"bfsId": 3101, "municipality": "Appenzell", "canton": "AI", "cantonId": 16, "income": 200000.0, "values": [26593.0, 26169.0, 25679.0]}, {"bfsId": 3101, "municipality": "Appenzell", "canton": "AI", "cantonId": 16, "income": 250000.0, "values": [39073.0, 38497.0, 37875.0]}, {"bfsId": 3101, "municipality": "Appenzell", "canton": "AI", "cantonId": 16, "income": 300000.0, "values": [51584.0, 50856.0, 50044.0]}, {"bfsId": 3101, "municipality": "Appenzell", "canton": "AI", "cantonId": 16, "income": 400000.0, "values": [76003.0, 75018.0, 73892.0]}, {"bfsId": 3101, "municipality": "Appenzell", "canton": "AI", "cantonId": 16, "income": 500000.0, "values": [99951.0, 98720.0, 97268.0]}, {"bfsId": 3101, "municipality": "Appenzell", "canton": "AI", "cantonId": 16, "income": 750000.0, "values": [158750.0, 156871.0, 154695.0]}, {"bfsId": 3101, "municipality": "Appenzell", "canton": "AI", "cantonId": 16, "income": 1000000.0, "values": [217549.0, 215023.0, 212095.0]}, {"bfsId": 3101, "municipality": "Appenzell", "canton": "AI", "cantonId": 16, "income": 5000000.0, "values": [1103786.0, 1091109.0, 1076336.0]}, {"bfsId": 3101, "municipality": "Appenzell", "canton": "AI", "cantonId": 16, "income": 10000000.0, "values": [2211541.0, 2186148.0, 2156573.0]}, {"bfsId": 3101, "municipality": "Appenzell", "canton": "AI", "cantonId": 16, "income": 50000000.0, "values": [11073671.0, 10946554.0, 10798469.0]}, {"bfsId": 3101, "municipality": "Appenzell", "canton": "AI", "cantonId": 16, "income": 100000000.0, "values": [22151334.0, 21897062.0, 21600839.0]}, {"bfsId": 3203, "municipality": "St. Gallen", "canton": "SG", "cantonId": 17, "income": 15000.0, "values": [0.0, 0.0, 0.0]}, {"bfsId": 3203, "municipality": "St. Gallen", "canton": "SG", "cantonId": 17, "income": 20000.0, "values": [0.0, 0.0, 0.0]}, {"bfsId": 3203, "municipality": "St. Gallen", "canton": "SG", "cantonId": 17, "income": 25000.0, "values": [0.0, 0.0, 0.0]}, {"bfsId": 3203, "municipality": "St. Gallen", "canton": "SG", "cantonId": 17, "income": 30000.0, "values": [0.0, 0.0, 0.0]}, {"bfsId": 3203, "municipality": "St. Gallen", "canton": "SG", "cantonId": 17, "income": 35000.0, "values": [0.0, 0.0, 0.0]}, {"bfsId": 3203, "municipality": "St. Gallen", "canton": "SG", "cantonId": 17, "income": 40000.0, "values": [144.0, 62.0, 62.0]}, {"bfsId": 3203, "municipality": "St. Gallen", "canton": "SG", "cantonId": 17, "income": 45000.0, "values": [614.0, 514.0, 514.0]}, {"bfsId": 3203, "municipality": "St. Gallen", "canton": "SG", "cantonId": 17, "income": 50000.0, "values": [1188.0, 1037.0, 1037.0]}, {"bfsId": 3203, "municipality": "St. Gallen", "canton": "SG", "cantonId": 17, "income": 60000.0, "values": [2540.0, 2391.0, 2391.0]}, {"bfsId": 3203, "municipality": "St. Gallen", "canton": "SG", "cantonId": 17, "income": 70000.0, "values": [3898.0, 3769.0, 3745.0]}, {"bfsId": 3203, "municipality": "St. Gallen", "canton": "SG", "cantonId": 17, "income": 80000.0, "values": [5449.0, 5314.0, 5314.0]}, {"bfsId": 3203, "municipality": "St. Gallen", "canton": "SG", "cantonId": 17, "income": 90000.0, "values": [7278.0, 7077.0, 7067.0]}, {"bfsId": 3203, "municipality": "St. Gallen", "canton": "SG", "cantonId": 17, "income": 100000.0, "values": [9411.0, 9199.0, 9199.0]}, {"bfsId": 3203, "municipality": "St. Gallen", "canton": "SG", "cantonId": 17, "income": 125000.0, "values": [14981.0, 14766.0, 14752.0]}, {"bfsId": 3203, "municipality": "St. Gallen", "canton": "SG", "cantonId": 17, "income": 150000.0, "values": [21149.0, 20899.0, 20899.0]}, {"bfsId": 3203, "municipality": "St. Gallen", "canton": "SG", "cantonId": 17, "income": 175000.0, "values": [28571.0, 28283.0, 28283.0]}, {"bfsId": 3203, "municipality": "St. Gallen", "canton": "SG", "cantonId": 17, "income": 200000.0, "values": [36872.0, 36567.0, 36537.0]}, {"bfsId": 3203, "municipality": "St. Gallen", "canton": "SG", "cantonId": 17, "income": 250000.0, "values": [53602.0, 53261.0, 53261.0]}, {"bfsId": 3203, "municipality": "St. Gallen", "canton": "SG", "cantonId": 17, "income": 300000.0, "values": [70462.0, 70088.0, 70047.0]}, {"bfsId": 3203, "municipality": "St. Gallen", "canton": "SG", "cantonId": 17, "income": 400000.0, "values": [104117.0, 103702.0, 103668.0]}, {"bfsId": 3203, "municipality": "St. Gallen", "canton": "SG", "cantonId": 17, "income": 500000.0, "values": [137811.0, 137357.0, 137282.0]}, {"bfsId": 3203, "municipality": "St. Gallen", "canton": "SG", "cantonId": 17, "income": 750000.0, "values": [218173.0, 217617.0, 217547.0]}, {"bfsId": 3203, "municipality": "St. Gallen", "canton": "SG", "cantonId": 17, "income": 1000000.0, "values": [297148.0, 296452.0, 296348.0]}, {"bfsId": 3203, "municipality": "St. Gallen", "canton": "SG", "cantonId": 17, "income": 5000000.0, "values": [1506173.0, 1503504.0, 1503072.0]}, {"bfsId": 3203, "municipality": "St. Gallen", "canton": "SG", "cantonId": 17, "income": 10000000.0, "values": [3017407.0, 3012244.0, 3011413.0]}, {"bfsId": 3203, "municipality": "St. Gallen", "canton": "SG", "cantonId": 17, "income": 50000000.0, "values": [15107417.0, 15082298.0, 15078141.0]}, {"bfsId": 3203, "municipality": "St. Gallen", "canton": "SG", "cantonId": 17, "income": 100000000.0, "values": [30219930.0, 30169866.0, 30161551.0]}, {"bfsId": 3901, "municipality": "Chur", "canton": "GR", "cantonId": 18, "income": 15000.0, "values": [0.0, 0.0, 0.0]}, {"bfsId": 3901, "municipality": "Chur", "canton": "GR", "cantonId": 18, "income": 20000.0, "values": [0.0, 0.0, 0.0]}, {"bfsId": 3901, "municipality": "Chur", "canton": "GR", "cantonId": 18, "income": 25000.0, "values": [0.0, 0.0, 0.0]}, {"bfsId": 3901, "municipality": "Chur", "canton": "GR", "cantonId": 18, "income": 30000.0, "values": [0.0, 0.0, 0.0]}, {"bfsId": 3901, "municipality": "Chur", "canton": "GR", "cantonId": 18, "income": 35000.0, "values": [0.0, 0.0, 0.0]}, {"bfsId": 3901, "municipality": "Chur", "canton": "GR", "cantonId": 18, "income": 40000.0, "values": [0.0, 0.0, 0.0]}, {"bfsId": 3901, "municipality": "Chur", "canton": "GR", "cantonId": 18, "income": 45000.0, "values": [0.0, 0.0, 0.0]}, {"bfsId": 3901, "municipality": "Chur", "canton": "GR", "cantonId": 18, "income": 50000.0, "values": [64.0, 15.0, 15.0]}, {"bfsId": 3901, "municipality": "Chur", "canton": "GR", "cantonId": 18, "income": 60000.0, "values": [940.0, 805.0, 805.0]}, {"bfsId": 3901, "municipality": "Chur", "canton": "GR", "cantonId": 18, "income": 70000.0, "values": [2203.0, 2040.0, 2040.0]}, {"bfsId": 3901, "municipality": "Chur", "canton": "GR", "cantonId": 18, "income": 80000.0, "values": [3752.0, 3574.0, 3572.0]}, {"bfsId": 3901, "municipality": "Chur", "canton": "GR", "cantonId": 18, "income": 90000.0, "values": [5470.0, 5276.0, 5272.0]}, {"bfsId": 3901, "municipality": "Chur", "canton": "GR", "cantonId": 18, "income": 100000.0, "values": [7324.0, 7115.0, 7111.0]}, {"bfsId": 3901, "municipality": "Chur", "canton": "GR", "cantonId": 18, "income": 125000.0, "values": [12597.0, 12361.0, 12355.0]}, {"bfsId": 3901, "municipality": "Chur", "canton": "GR", "cantonId": 18, "income": 150000.0, "values": [18311.0, 18058.0, 18050.0]}, {"bfsId": 3901, "municipality": "Chur", "canton": "GR", "cantonId": 18, "income": 175000.0, "values": [24891.0, 24606.0, 24599.0]}, {"bfsId": 3901, "municipality": "Chur", "canton": "GR", "cantonId": 18, "income": 200000.0, "values": [32382.0, 32085.0, 32063.0]}, {"bfsId": 3901, "municipality": "Chur", "canton": "GR", "cantonId": 18, "income": 250000.0, "values": [47567.0, 47229.0, 47216.0]}, {"bfsId": 3901, "municipality": "Chur", "canton": "GR", "cantonId": 18, "income": 300000.0, "values": [63049.0, 62684.0, 62655.0]}, {"bfsId": 3901, "municipality": "Chur", "canton": "GR", "cantonId": 18, "income": 400000.0, "values": [93988.0, 93577.0, 93544.0]}, {"bfsId": 3901, "municipality": "Chur", "canton": "GR", "cantonId": 18, "income": 500000.0, "values": [125028.0, 124568.0, 124516.0]}, {"bfsId": 3901, "municipality": "Chur", "canton": "GR", "cantonId": 18, "income": 750000.0, "values": [202974.0, 202380.0, 202314.0]}, {"bfsId": 3901, "municipality": "Chur", "canton": "GR", "cantonId": 18, "income": 1000000.0, "values": [281614.0, 280879.0, 280786.0]}, {"bfsId": 3901, "municipality": "Chur", "canton": "GR", "cantonId": 18, "income": 5000000.0, "values": [1456914.0, 1454500.0, 1454091.0]}, {"bfsId": 3901, "municipality": "Chur", "canton": "GR", "cantonId": 18, "income": 10000000.0, "values": [2919085.0, 2914258.0, 2913454.0]}, {"bfsId": 3901, "municipality": "Chur", "canton": "GR", "cantonId": 18, "income": 50000000.0, "values": [14616515.0, 14592380.0, 14588358.0]}, {"bfsId": 3901, "municipality": "Chur", "canton": "GR", "cantonId": 18, "income": 100000000.0, "values": [29238303.0, 29190033.0, 29181988.0]}, {"bfsId": 4001, "municipality": "Aarau", "canton": "AG", "cantonId": 19, "income": 15000.0, "values": [0.0, 0.0, 0.0]}, {"bfsId": 4001, "municipality": "Aarau", "canton": "AG", "cantonId": 19, "income": 20000.0, "values": [0.0, 0.0, 0.0]}, {"bfsId": 4001, "municipality": "Aarau", "canton": "AG", "cantonId": 19, "income": 25000.0, "values": [0.0, 0.0, 0.0]}, {"bfsId": 4001, "municipality": "Aarau", "canton": "AG", "cantonId": 19, "income": 30000.0, "values": [25.0, 23.0, 23.0]}, {"bfsId": 4001, "municipality": "Aarau", "canton": "AG", "cantonId": 19, "income": 35000.0, "values": [272.0, 263.0, 263.0]}, {"bfsId": 4001, "municipality": "Aarau", "canton": "AG", "cantonId": 19, "income": 40000.0, "values": [521.0, 506.0, 506.0]}, {"bfsId": 4001, "municipality": "Aarau", "canton": "AG", "cantonId": 19, "income": 45000.0, "values": [866.0, 782.0, 782.0]}, {"bfsId": 4001, "municipality": "Aarau", "canton": "AG", "cantonId": 19, "income": 50000.0, "values": [1200.0, 1174.0, 1174.0]}, {"bfsId": 4001, "municipality": "Aarau", "canton": "AG", "cantonId": 19, "income": 60000.0, "values": [2115.0, 2082.0, 2082.0]}, {"bfsId": 4001, "municipality": "Aarau", "canton": "AG", "cantonId": 19, "income": 70000.0, "values": [3127.0, 3085.0, 3072.0]}, {"bfsId": 4001, "municipality": "Aarau", "canton": "AG", "cantonId": 19, "income": 80000.0, "values": [4402.0, 4357.0, 4357.0]}, {"bfsId": 4001, "municipality": "Aarau", "canton": "AG", "cantonId": 19, "income": 90000.0, "values": [5905.0, 5830.0, 5830.0]}, {"bfsId": 4001, "municipality": "Aarau", "canton": "AG", "cantonId": 19, "income": 100000.0, "values": [7468.0, 7391.0, 7391.0]}, {"bfsId": 4001, "municipality": "Aarau", "canton": "AG", "cantonId": 19, "income": 125000.0, "values": [12111.0, 12008.0, 12008.0]}, {"bfsId": 4001, "municipality": "Aarau", "canton": "AG", "cantonId": 19, "income": 150000.0, "values": [17364.0, 17245.0, 17245.0]}, {"bfsId": 4001, "municipality": "Aarau", "canton": "AG", "cantonId": 19, "income": 175000.0, "values": [23744.0, 23572.0, 23572.0]}, {"bfsId": 4001, "municipality": "Aarau", "canton": "AG", "cantonId": 19, "income": 200000.0, "values": [31199.0, 31024.0, 30991.0]}, {"bfsId": 4001, "municipality": "Aarau", "canton": "AG", "cantonId": 19, "income": 250000.0, "values": [46176.0, 45950.0, 45950.0]}, {"bfsId": 4001, "municipality": "Aarau", "canton": "AG", "cantonId": 19, "income": 300000.0, "values": [61600.0, 61340.0, 61306.0]}, {"bfsId": 4001, "municipality": "Aarau", "canton": "AG", "cantonId": 19, "income": 400000.0, "values": [92566.0, 92245.0, 92209.0]}, {"bfsId": 4001, "municipality": "Aarau", "canton": "AG", "cantonId": 19, "income": 500000.0, "values": [124331.0, 123975.0, 123904.0]}, {"bfsId": 4001, "municipality": "Aarau", "canton": "AG", "cantonId": 19, "income": 750000.0, "values": [203771.0, 203230.0, 203160.0]}, {"bfsId": 4001, "municipality": "Aarau", "canton": "AG", "cantonId": 19, "income": 1000000.0, "values": [285542.0, 284849.0, 284741.0]}, {"bfsId": 4001, "municipality": "Aarau", "canton": "AG", "cantonId": 19, "income": 5000000.0, "values": [1539277.0, 1536537.0, 1536089.0]}, {"bfsId": 4001, "municipality": "Aarau", "canton": "AG", "cantonId": 19, "income": 10000000.0, "values": [3106398.0, 3101073.0, 3100211.0]}, {"bfsId": 4001, "municipality": "Aarau", "canton": "AG", "cantonId": 19, "income": 50000000.0, "values": [15643513.0, 15617494.0, 15613183.0]}, {"bfsId": 4001, "municipality": "Aarau", "canton": "AG", "cantonId": 19, "income": 100000000.0, "values": [31314907.0, 31263020.0, 31254398.0]}, {"bfsId": 4566, "municipality": "Frauenfeld", "canton": "TG", "cantonId": 20, "income": 15000.0, "values": [0.0, 0.0, 0.0]}, {"bfsId": 4566, "municipality": "Frauenfeld", "canton": "TG", "cantonId": 20, "income": 20000.0, "values": [0.0, 0.0, 0.0]}, {"bfsId": 4566, "municipality": "Frauenfeld", "canton": "TG", "cantonId": 20, "income": 25000.0, "values": [0.0, 0.0, 0.0]}, {"bfsId": 4566, "municipality": "Frauenfeld", "canton": "TG", "cantonId": 20, "income": 30000.0, "values": [0.0, 0.0, 0.0]}, {"bfsId": 4566, "municipality": "Frauenfeld", "canton": "TG", "cantonId": 20, "income": 35000.0, "values": [0.0, 0.0, 0.0]}, {"bfsId": 4566, "municipality": "Frauenfeld", "canton": "TG", "cantonId": 20, "income": 40000.0, "values": [0.0, 0.0, 0.0]}, {"bfsId": 4566, "municipality": "Frauenfeld", "canton": "TG", "cantonId": 20, "income": 45000.0, "values": [241.0, 209.0, 209.0]}, {"bfsId": 4566, "municipality": "Frauenfeld", "canton": "TG", "cantonId": 20, "income": 50000.0, "values": [597.0, 538.0, 538.0]}, {"bfsId": 4566, "municipality": "Frauenfeld", "canton": "TG", "cantonId": 20, "income": 60000.0, "values": [1685.0, 1587.0, 1587.0]}, {"bfsId": 4566, "municipality": "Frauenfeld", "canton": "TG", "cantonId": 20, "income": 70000.0, "values": [3090.0, 2971.0, 2965.0]}, {"bfsId": 4566, "municipality": "Frauenfeld", "canton": "TG", "cantonId": 20, "income": 80000.0, "values": [4634.0, 4513.0, 4513.0]}, {"bfsId": 4566, "municipality": "Frauenfeld", "canton": "TG", "cantonId": 20, "income": 90000.0, "values": [6251.0, 6119.0, 6119.0]}, {"bfsId": 4566, "municipality": "Frauenfeld", "canton": "TG", "cantonId": 20, "income": 100000.0, "values": [8072.0, 7918.0, 7918.0]}, {"bfsId": 4566, "municipality": "Frauenfeld", "canton": "TG", "cantonId": 20, "income": 125000.0, "values": [13023.0, 12867.0, 12867.0]}, {"bfsId": 4566, "municipality": "Frauenfeld", "canton": "TG", "cantonId": 20, "income": 150000.0, "values": [18352.0, 18191.0, 18191.0]}, {"bfsId": 4566, "municipality": "Frauenfeld", "canton": "TG", "cantonId": 20, "income": 175000.0, "values": [24568.0, 24362.0, 24362.0]}, {"bfsId": 4566, "municipality": "Frauenfeld", "canton": "TG", "cantonId": 20, "income": 200000.0, "values": [31726.0, 31516.0, 31478.0]}, {"bfsId": 4566, "municipality": "Frauenfeld", "canton": "TG", "cantonId": 20, "income": 250000.0, "values": [46516.0, 46269.0, 46269.0]}, {"bfsId": 4566, "municipality": "Frauenfeld", "canton": "TG", "cantonId": 20, "income": 300000.0, "values": [61342.0, 61059.0, 61029.0]}, {"bfsId": 4566, "municipality": "Frauenfeld", "canton": "TG", "cantonId": 20, "income": 400000.0, "values": [91533.0, 91205.0, 91167.0]}, {"bfsId": 4566, "municipality": "Frauenfeld", "canton": "TG", "cantonId": 20, "income": 500000.0, "values": [122327.0, 121968.0, 121900.0]}, {"bfsId": 4566, "municipality": "Frauenfeld", "canton": "TG", "cantonId": 20, "income": 750000.0, "values": [199304.0, 198807.0, 198740.0]}, {"bfsId": 4566, "municipality": "Frauenfeld", "canton": "TG", "cantonId": 20, "income": 1000000.0, "values": [276280.0, 275648.0, 275544.0]}, {"bfsId": 4566, "municipality": "Frauenfeld", "canton": "TG", "cantonId": 20, "income": 5000000.0, "values": [1453317.0, 1450764.0, 1450344.0]}, {"bfsId": 4566, "municipality": "Frauenfeld", "canton": "TG", "cantonId": 20, "income": 10000000.0, "values": [2924568.0, 2919586.0, 2918777.0]}, {"bfsId": 4566, "municipality": "Frauenfeld", "canton": "TG", "cantonId": 20, "income": 50000000.0, "values": [14694698.0, 14670288.0, 14666241.0]}, {"bfsId": 4566, "municipality": "Frauenfeld", "canton": "TG", "cantonId": 20, "income": 100000000.0, "values": [29407361.0, 29358666.0, 29350571.0]}, {"bfsId": 5002, "municipality": "Bellinzona", "canton": "TI", "cantonId": 21, "income": 15000.0, "values": [20.0, 20.0, 20.0]}, {"bfsId": 5002, "municipality": "Bellinzona", "canton": "TI", "cantonId": 21, "income": 20000.0, "values": [20.0, 20.0, 20.0]}, {"bfsId": 5002, "municipality": "Bellinzona", "canton": "TI", "cantonId": 21, "income": 25000.0, "values": [20.0, 20.0, 20.0]}, {"bfsId": 5002, "municipality": "Bellinzona", "canton": "TI", "cantonId": 21, "income": 30000.0, "values": [20.0, 20.0, 20.0]}, {"bfsId": 5002, "municipality": "Bellinzona", "canton": "TI", "cantonId": 21, "income": 35000.0, "values": [20.0, 20.0, 20.0]}, {"bfsId": 5002, "municipality": "Bellinzona", "canton": "TI", "cantonId": 21, "income": 40000.0, "values": [20.0, 20.0, 20.0]}, {"bfsId": 5002, "municipality": "Bellinzona", "canton": "TI", "cantonId": 21, "income": 45000.0, "values": [276.0, 265.0, 265.0]}, {"bfsId": 5002, "municipality": "Bellinzona", "canton": "TI", "cantonId": 21, "income": 50000.0, "values": [639.0, 621.0, 621.0]}, {"bfsId": 5002, "municipality": "Bellinzona", "canton": "TI", "cantonId": 21, "income": 60000.0, "values": [1197.0, 1171.0, 1171.0]}, {"bfsId": 5002, "municipality": "Bellinzona", "canton": "TI", "cantonId": 21, "income": 70000.0, "values": [2072.0, 2028.0, 2016.0]}, {"bfsId": 5002, "municipality": "Bellinzona", "canton": "TI", "cantonId": 21, "income": 80000.0, "values": [3583.0, 3513.0, 3513.0]}, {"bfsId": 5002, "municipality": "Bellinzona", "canton": "TI", "cantonId": 21, "income": 90000.0, "values": [5390.0, 5287.0, 5267.0]}, {"bfsId": 5002, "municipality": "Bellinzona", "canton": "TI", "cantonId": 21, "income": 100000.0, "values": [7466.0, 7314.0, 7314.0]}, {"bfsId": 5002, "municipality": "Bellinzona", "canton": "TI", "cantonId": 21, "income": 125000.0, "values": [13429.0, 13189.0, 13164.0]}, {"bfsId": 5002, "municipality": "Bellinzona", "canton": "TI", "cantonId": 21, "income": 150000.0, "values": [20334.0, 20003.0, 20003.0]}, {"bfsId": 5002, "municipality": "Bellinzona", "canton": "TI", "cantonId": 21, "income": 175000.0, "values": [27850.0, 27386.0, 27386.0]}, {"bfsId": 5002, "municipality": "Bellinzona", "canton": "TI", "cantonId": 21, "income": 200000.0, "values": [36547.0, 35991.0, 35953.0]}, {"bfsId": 5002, "municipality": "Bellinzona", "canton": "TI", "cantonId": 21, "income": 250000.0, "values": [54479.0, 53691.0, 53691.0]}, {"bfsId": 5002, "municipality": "Bellinzona", "canton": "TI", "cantonId": 21, "income": 300000.0, "values": [73045.0, 72016.0, 71975.0]}, {"bfsId": 5002, "municipality": "Bellinzona", "canton": "TI", "cantonId": 21, "income": 400000.0, "values": [110688.0, 109213.0, 109171.0]}, {"bfsId": 5002, "municipality": "Bellinzona", "canton": "TI", "cantonId": 21, "income": 500000.0, "values": [148642.0, 146719.0, 146636.0]}, {"bfsId": 5002, "municipality": "Bellinzona", "canton": "TI", "cantonId": 21, "income": 750000.0, "values": [243505.0, 240401.0, 240318.0]}, {"bfsId": 5002, "municipality": "Bellinzona", "canton": "TI", "cantonId": 21, "income": 1000000.0, "values": [338910.0, 334612.0, 334487.0]}, {"bfsId": 5002, "municipality": "Bellinzona", "canton": "TI", "cantonId": 21, "income": 5000000.0, "values": [1814623.0, 1791499.0, 1790977.0]}, {"bfsId": 5002, "municipality": "Bellinzona", "canton": "TI", "cantonId": 21, "income": 10000000.0, "values": [3659214.0, 3612529.0, 3611525.0]}, {"bfsId": 5002, "municipality": "Bellinzona", "canton": "TI", "cantonId": 21, "income": 50000000.0, "values": [18416107.0, 18180931.0, 18175914.0]}, {"bfsId": 5002, "municipality": "Bellinzona", "canton": "TI", "cantonId": 21, "income": 100000000.0, "values": [36862224.0, 36391435.0, 36381399.0]}, {"bfsId": 5586, "municipality": "Lausanne", "canton": "VD", "cantonId": 22, "income": 15000.0, "values": [0.0, 0.0, 0.0]}, {"bfsId": 5586, "municipality": "Lausanne", "canton": "VD", "cantonId": 22, "income": 20000.0, "values": [0.0, 0.0, 0.0]}, {"bfsId": 5586, "municipality": "Lausanne", "canton": "VD", "cantonId": 22, "income": 25000.0, "values": [0.0, 0.0, 0.0]}, {"bfsId": 5586, "municipality": "Lausanne", "canton": "VD", "cantonId": 22, "income": 30000.0, "values": [0.0, 0.0, 0.0]}, {"bfsId": 5586, "municipality": "Lausanne", "canton": "VD", "cantonId": 22, "income": 35000.0, "values": [38.0, 0.0, 0.0]}, {"bfsId": 5586, "municipality": "Lausanne", "canton": "VD", "cantonId": 22, "income": 40000.0, "values": [357.0, 241.0, 240.0]}, {"bfsId": 5586, "municipality": "Lausanne", "canton": "VD", "cantonId": 22, "income": 45000.0, "values": [946.0, 777.0, 773.0]}, {"bfsId": 5586, "municipality": "Lausanne", "canton": "VD", "cantonId": 22, "income": 50000.0, "values": [1702.0, 1485.0, 1479.0]}, {"bfsId": 5586, "municipality": "Lausanne", "canton": "VD", "cantonId": 22, "income": 60000.0, "values": [3678.0, 3399.0, 3384.0]}, {"bfsId": 5586, "municipality": "Lausanne", "canton": "VD", "cantonId": 22, "income": 70000.0, "values": [5938.0, 5602.0, 5578.0]}, {"bfsId": 5586, "municipality": "Lausanne", "canton": "VD", "cantonId": 22, "income": 80000.0, "values": [8549.0, 8331.0, 8282.0]}, {"bfsId": 5586, "municipality": "Lausanne", "canton": "VD", "cantonId": 22, "income": 90000.0, "values": [10768.0, 10528.0, 10485.0]}, {"bfsId": 5586, "municipality": "Lausanne", "canton": "VD", "cantonId": 22, "income": 100000.0, "values": [13180.0, 12979.0, 12927.0]}, {"bfsId": 5586, "municipality": "Lausanne", "canton": "VD", "cantonId": 22, "income": 125000.0, "values": [18840.0, 18618.0, 18546.0]}, {"bfsId": 5586, "municipality": "Lausanne", "canton": "VD", "cantonId": 22, "income": 150000.0, "values": [25366.0, 25144.0, 25050.0]}, {"bfsId": 5586, "municipality": "Lausanne", "canton": "VD", "cantonId": 22, "income": 175000.0, "values": [33503.0, 33226.0, 33106.0]}, {"bfsId": 5586, "municipality": "Lausanne", "canton": "VD", "cantonId": 22, "income": 200000.0, "values": [43205.0, 42919.0, 42738.0]}, {"bfsId": 5586, "municipality": "Lausanne", "canton": "VD", "cantonId": 22, "income": 250000.0, "values": [62740.0, 62450.0, 62243.0]}, {"bfsId": 5586, "municipality": "Lausanne", "canton": "VD", "cantonId": 22, "income": 300000.0, "values": [83528.0, 83226.0, 82918.0]}, {"bfsId": 5586, "municipality": "Lausanne", "canton": "VD", "cantonId": 22, "income": 400000.0, "values": [126421.0, 126186.0, 125733.0]}, {"bfsId": 5586, "municipality": "Lausanne", "canton": "VD", "cantonId": 22, "income": 500000.0, "values": [171386.0, 171207.0, 170557.0]}, {"bfsId": 5586, "municipality": "Lausanne", "canton": "VD", "cantonId": 22, "income": 750000.0, "values": [274797.0, 274017.0, 273935.0]}, {"bfsId": 5586, "municipality": "Lausanne", "canton": "VD", "cantonId": 22, "income": 1000000.0, "values": [372490.0, 371545.0, 371430.0]}, {"bfsId": 5586, "municipality": "Lausanne", "canton": "VD", "cantonId": 22, "income": 5000000.0, "values": [1881038.0, 1877625.0, 1877102.0]}, {"bfsId": 5586, "municipality": "Lausanne", "canton": "VD", "cantonId": 22, "income": 10000000.0, "values": [3766688.0, 3760164.0, 3759127.0]}, {"bfsId": 5586, "municipality": "Lausanne", "canton": "VD", "cantonId": 22, "income": 50000000.0, "values": [18851938.0, 18820513.0, 18815326.0]}, {"bfsId": 5586, "municipality": "Lausanne", "canton": "VD", "cantonId": 22, "income": 100000000.0, "values": [37708502.0, 37645952.0, 37635577.0]}, {"bfsId": 6266, "municipality": "Sion", "canton": "VS", "cantonId": 23, "income": 15000.0, "values": [34.0, 34.0, 34.0]}, {"bfsId": 6266, "municipality": "Sion", "canton": "VS", "cantonId": 23, "income": 20000.0, "values": [34.0, 34.0, 34.0]}, {"bfsId": 6266, "municipality": "Sion", "canton": "VS", "cantonId": 23, "income": 25000.0, "values": [34.0, 34.0, 34.0]}, {"bfsId": 6266, "municipality": "Sion", "canton": "VS", "cantonId": 23, "income": 30000.0, "values": [34.0, 34.0, 34.0]}, {"bfsId": 6266, "municipality": "Sion", "canton": "VS", "cantonId": 23, "income": 35000.0, "values": [34.0, 34.0, 34.0]}, {"bfsId": 6266, "municipality": "Sion", "canton": "VS", "cantonId": 23, "income": 40000.0, "values": [34.0, 34.0, 34.0]}, {"bfsId": 6266, "municipality": "Sion", "canton": "VS", "cantonId": 23, "income": 45000.0, "values": [230.0, 225.0, 225.0]}, {"bfsId": 6266, "municipality": "Sion", "canton": "VS", "cantonId": 23, "income": 50000.0, "values": [683.0, 669.0, 669.0]}, {"bfsId": 6266, "municipality": "Sion", "canton": "VS", "cantonId": 23, "income": 60000.0, "values": [2005.0, 1988.0, 1988.0]}, {"bfsId": 6266, "municipality": "Sion", "canton": "VS", "cantonId": 23, "income": 70000.0, "values": [3078.0, 3066.0, 3053.0]}, {"bfsId": 6266, "municipality": "Sion", "canton": "VS", "cantonId": 23, "income": 80000.0, "values": [4423.0, 4406.0, 4406.0]}, {"bfsId": 6266, "municipality": "Sion", "canton": "VS", "cantonId": 23, "income": 90000.0, "values": [5915.0, 5879.0, 5879.0]}, {"bfsId": 6266, "municipality": "Sion", "canton": "VS", "cantonId": 23, "income": 100000.0, "values": [7537.0, 7497.0, 7497.0]}, {"bfsId": 6266, "municipality": "Sion", "canton": "VS", "cantonId": 23, "income": 125000.0, "values": [12235.0, 12187.0, 12187.0]}, {"bfsId": 6266, "municipality": "Sion", "canton": "VS", "cantonId": 23, "income": 150000.0, "values": [17876.0, 17821.0, 17821.0]}, {"bfsId": 6266, "municipality": "Sion", "canton": "VS", "cantonId": 23, "income": 175000.0, "values": [26341.0, 26215.0, 26215.0]}, {"bfsId": 6266, "municipality": "Sion", "canton": "VS", "cantonId": 23, "income": 200000.0, "values": [35703.0, 35584.0, 35545.0]}, {"bfsId": 6266, "municipality": "Sion", "canton": "VS", "cantonId": 23, "income": 250000.0, "values": [53307.0, 53154.0, 53154.0]}, {"bfsId": 6266, "municipality": "Sion", "canton": "VS", "cantonId": 23, "income": 300000.0, "values": [70962.0, 70766.0, 70727.0]}, {"bfsId": 6266, "municipality": "Sion", "canton": "VS", "cantonId": 23, "income": 400000.0, "values": [107241.0, 106997.0, 106956.0]}, {"bfsId": 6266, "municipality": "Sion", "canton": "VS", "cantonId": 23, "income": 500000.0, "values": [142412.0, 142146.0, 142070.0]}, {"bfsId": 6266, "municipality": "Sion", "canton": "VS", "cantonId": 23, "income": 750000.0, "values": [228748.0, 228330.0, 228254.0]}, {"bfsId": 6266, "municipality": "Sion", "canton": "VS", "cantonId": 23, "income": 1000000.0, "values": [315084.0, 314514.0, 314400.0]}, {"bfsId": 6266, "municipality": "Sion", "canton": "VS", "cantonId": 23, "income": 5000000.0, "values": [1641883.0, 1639145.0, 1638671.0]}, {"bfsId": 6266, "municipality": "Sion", "canton": "VS", "cantonId": 23, "income": 10000000.0, "values": [3300333.0, 3294858.0, 3293946.0]}, {"bfsId": 6266, "municipality": "Sion", "canton": "VS", "cantonId": 23, "income": 50000000.0, "values": [16568083.0, 16540708.0, 16536146.0]}, {"bfsId": 6266, "municipality": "Sion", "canton": "VS", "cantonId": 23, "income": 100000000.0, "values": [33152771.0, 33098021.0, 33088896.0]}, {"bfsId": 6458, "municipality": "Neuchâtel", "canton": "NE", "cantonId": 24, "income": 15000.0, "values": [0.0, 0.0, 0.0]}, {"bfsId": 6458, "municipality": "Neuchâtel", "canton": "NE", "cantonId": 24, "income": 20000.0, "values": [0.0, 0.0, 0.0]}, {"bfsId": 6458, "municipality": "Neuchâtel", "canton": "NE", "cantonId": 24, "income": 25000.0, "values": [10.0, 0.0, 0.0]}, {"bfsId": 6458, "municipality": "Neuchâtel", "canton": "NE", "cantonId": 24, "income": 30000.0, "values": [69.0, 10.0, 0.0]}, {"bfsId": 6458, "municipality": "Neuchâtel", "canton": "NE", "cantonId": 24, "income": 35000.0, "values": [232.0, 88.0, 63.0]}, {"bfsId": 6458, "municipality": "Neuchâtel", "canton": "NE", "cantonId": 24, "income": 40000.0, "values": [602.0, 429.0, 352.0]}, {"bfsId": 6458, "municipality": "Neuchâtel", "canton": "NE", "cantonId": 24, "income": 45000.0, "values": [1118.0, 916.0, 718.0]}, {"bfsId": 6458, "municipality": "Neuchâtel", "canton": "NE", "cantonId": 24, "income": 50000.0, "values": [1859.0, 1663.0, 1476.0]}, {"bfsId": 6458, "municipality": "Neuchâtel", "canton": "NE", "cantonId": 24, "income": 60000.0, "values": [3719.0, 3463.0, 3151.0]}, {"bfsId": 6458, "municipality": "Neuchâtel", "canton": "NE", "cantonId": 24, "income": 70000.0, "values": [5751.0, 5430.0, 5073.0]}, {"bfsId": 6458, "municipality": "Neuchâtel", "canton": "NE", "cantonId": 24, "income": 80000.0, "values": [7960.0, 7567.0, 7218.0]}, {"bfsId": 6458, "municipality": "Neuchâtel", "canton": "NE", "cantonId": 24, "income": 90000.0, "values": [10292.0, 9764.0, 9408.0]}, {"bfsId": 6458, "municipality": "Neuchâtel", "canton": "NE", "cantonId": 24, "income": 100000.0, "values": [12700.0, 12060.0, 11683.0]}, {"bfsId": 6458, "municipality": "Neuchâtel", "canton": "NE", "cantonId": 24, "income": 125000.0, "values": [19140.0, 18206.0, 17771.0]}, {"bfsId": 6458, "municipality": "Neuchâtel", "canton": "NE", "cantonId": 24, "income": 150000.0, "values": [26167.0, 24966.0, 24464.0]}, {"bfsId": 6458, "municipality": "Neuchâtel", "canton": "NE", "cantonId": 24, "income": 175000.0, "values": [34345.0, 32892.0, 32319.0]}, {"bfsId": 6458, "municipality": "Neuchâtel", "canton": "NE", "cantonId": 24, "income": 200000.0, "values": [43590.0, 41956.0, 41280.0]}, {"bfsId": 6458, "municipality": "Neuchâtel", "canton": "NE", "cantonId": 24, "income": 250000.0, "values": [62633.0, 60576.0, 59766.0]}, {"bfsId": 6458, "municipality": "Neuchâtel", "canton": "NE", "cantonId": 24, "income": 300000.0, "values": [82198.0, 79765.0, 78810.0]}, {"bfsId": 6458, "municipality": "Neuchâtel", "canton": "NE", "cantonId": 24, "income": 400000.0, "values": [122151.0, 118990.0, 117817.0]}, {"bfsId": 6458, "municipality": "Neuchâtel", "canton": "NE", "cantonId": 24, "income": 500000.0, "values": [158865.0, 154886.0, 154758.0]}, {"bfsId": 6458, "municipality": "Neuchâtel", "canton": "NE", "cantonId": 24, "income": 750000.0, "values": [248836.0, 242545.0, 242416.0]}, {"bfsId": 6458, "municipality": "Neuchâtel", "canton": "NE", "cantonId": 24, "income": 1000000.0, "values": [338808.0, 330203.0, 330036.0]}, {"bfsId": 6458, "municipality": "Neuchâtel", "canton": "NE", "cantonId": 24, "income": 5000000.0, "values": [1723767.0, 1678422.0, 1677889.0]}, {"bfsId": 6458, "municipality": "Neuchâtel", "canton": "NE", "cantonId": 24, "income": 10000000.0, "values": [3454916.0, 3363621.0, 3362641.0]}, {"bfsId": 6458, "municipality": "Neuchâtel", "canton": "NE", "cantonId": 24, "income": 50000000.0, "values": [17304266.0, 16845355.0, 16840661.0]}, {"bfsId": 6458, "municipality": "Neuchâtel", "canton": "NE", "cantonId": 24, "income": 100000000.0, "values": [34615954.0, 33697525.0, 33688185.0]}, {"bfsId": 6621, "municipality": "Genève", "canton": "GE", "cantonId": 25, "income": 15000.0, "values": [25.0, 25.0, 25.0]}, {"bfsId": 6621, "municipality": "Genève", "canton": "GE", "cantonId": 25, "income": 20000.0, "values": [25.0, 25.0, 25.0]}, {"bfsId": 6621, "municipality": "Genève", "canton": "GE", "cantonId": 25, "income": 25000.0, "values": [25.0, 25.0, 25.0]}, {"bfsId": 6621, "municipality": "Genève", "canton": "GE", "cantonId": 25, "income": 30000.0, "values": [25.0, 25.0, 25.0]}, {"bfsId": 6621, "municipality": "Genève", "canton": "GE", "cantonId": 25, "income": 35000.0, "values": [25.0, 25.0, 25.0]}, {"bfsId": 6621, "municipality": "Genève", "canton": "GE", "cantonId": 25, "income": 40000.0, "values": [25.0, 25.0, 25.0]}, {"bfsId": 6621, "municipality": "Genève", "canton": "GE", "cantonId": 25, "income": 45000.0, "values": [25.0, 25.0, 25.0]}, {"bfsId": 6621, "municipality": "Genève", "canton": "GE", "cantonId": 25, "income": 50000.0, "values": [25.0, 25.0, 25.0]}, {"bfsId": 6621, "municipality": "Genève", "canton": "GE", "cantonId": 25, "income": 60000.0, "values": [233.0, 181.0, 210.0]}, {"bfsId": 6621, "municipality": "Genève", "canton": "GE", "cantonId": 25, "income": 70000.0, "values": [1521.0, 1461.0, 1493.0]}, {"bfsId": 6621, "municipality": "Genève", "canton": "GE", "cantonId": 25, "income": 80000.0, "values": [3312.0, 3229.0, 3269.0]}, {"bfsId": 6621, "municipality": "Genève", "canton": "GE", "cantonId": 25, "income": 90000.0, "values": [5440.0, 5340.0, 5384.0]}, {"bfsId": 6621, "municipality": "Genève", "canton": "GE", "cantonId": 25, "income": 100000.0, "values": [7741.0, 7625.0, 7675.0]}, {"bfsId": 6621, "municipality": "Genève", "canton": "GE", "cantonId": 25, "income": 125000.0, "values": [14345.0, 14190.0, 14253.0]}, {"bfsId": 6621, "municipality": "Genève", "canton": "GE", "cantonId": 25, "income": 150000.0, "values": [21636.0, 21467.0, 21528.0]}, {"bfsId": 6621, "municipality": "Genève", "canton": "GE", "cantonId": 25, "income": 175000.0, "values": [29695.0, 29494.0, 29554.0]}, {"bfsId": 6621, "municipality": "Genève", "canton": "GE", "cantonId": 25, "income": 200000.0, "values": [38786.0, 38560.0, 38612.0]}, {"bfsId": 6621, "municipality": "Genève", "canton": "GE", "cantonId": 25, "income": 250000.0, "values": [57104.0, 56844.0, 56906.0]}, {"bfsId": 6621, "municipality": "Genève", "canton": "GE", "cantonId": 25, "income": 300000.0, "values": [75545.0, 75231.0, 75288.0]}, {"bfsId": 6621, "municipality": "Genève", "canton": "GE", "cantonId": 25, "income": 400000.0, "values": [113159.0, 112763.0, 112828.0]}, {"bfsId": 6621, "municipality": "Genève", "canton": "GE", "cantonId": 25, "income": 500000.0, "values": [152012.0, 151527.0, 151590.0]}, {"bfsId": 6621, "municipality": "Genève", "canton": "GE", "cantonId": 25, "income": 750000.0, "values": [251759.0, 251016.0, 251113.0]}, {"bfsId": 6621, "municipality": "Genève", "canton": "GE", "cantonId": 25, "income": 1000000.0, "values": [354288.0, 353309.0, 353409.0]}, {"bfsId": 6621, "municipality": "Genève", "canton": "GE", "cantonId": 25, "income": 5000000.0, "values": [1986854.0, 1983099.0, 1982816.0]}, {"bfsId": 6621, "municipality": "Genève", "canton": "GE", "cantonId": 25, "income": 10000000.0, "values": [4031312.0, 4024183.0, 4023344.0]}, {"bfsId": 6621, "municipality": "Genève", "canton": "GE", "cantonId": 25, "income": 50000000.0, "values": [20387030.0, 20352905.0, 20347565.0]}, {"bfsId": 6621, "municipality": "Genève", "canton": "GE", "cantonId": 25, "income": 100000000.0, "values": [40831680.0, 40763809.0, 40752843.0]}, {"bfsId": 6711, "municipality": "Delémont", "canton": "JU", "cantonId": 26, "income": 15000.0, "values": [0.0, 0.0, 0.0]}, {"bfsId": 6711, "municipality": "Delémont", "canton": "JU", "cantonId": 26, "income": 20000.0, "values": [0.0, 0.0, 0.0]}, {"bfsId": 6711, "municipality": "Delémont", "canton": "JU", "cantonId": 26, "income": 25000.0, "values": [0.0, 0.0, 0.0]}, {"bfsId": 6711, "municipality": "Delémont", "canton": "JU", "cantonId": 26, "income": 30000.0, "values": [35.0, 30.0, 0.0]}, {"bfsId": 6711, "municipality": "Delémont", "canton": "JU", "cantonId": 26, "income": 35000.0, "values": [229.0, 218.0, 182.0]}, {"bfsId": 6711, "municipality": "Delémont", "canton": "JU", "cantonId": 26, "income": 40000.0, "values": [685.0, 649.0, 555.0]}, {"bfsId": 6711, "municipality": "Delémont", "canton": "JU", "cantonId": 26, "income": 45000.0, "values": [1176.0, 1135.0, 1035.0]}, {"bfsId": 6711, "municipality": "Delémont", "canton": "JU", "cantonId": 26, "income": 50000.0, "values": [1853.0, 1790.0, 1645.0]}, {"bfsId": 6711, "municipality": "Delémont", "canton": "JU", "cantonId": 26, "income": 60000.0, "values": [3270.0, 3192.0, 3015.0]}, {"bfsId": 6711, "municipality": "Delémont", "canton": "JU", "cantonId": 26, "income": 70000.0, "values": [4785.0, 4667.0, 4437.0]}, {"bfsId": 6711, "municipality": "Delémont", "canton": "JU", "cantonId": 26, "income": 80000.0, "values": [6763.0, 6624.0, 6374.0]}, {"bfsId": 6711, "municipality": "Delémont", "canton": "JU", "cantonId": 26, "income": 90000.0, "values": [8826.0, 8664.0, 8394.0]}, {"bfsId": 6711, "municipality": "Delémont", "canton": "JU", "cantonId": 26, "income": 100000.0, "values": [10939.0, 10754.0, 10464.0]}, {"bfsId": 6711, "municipality": "Delémont", "canton": "JU", "cantonId": 26, "income": 125000.0, "values": [16852.0, 16566.0, 16194.0]}, {"bfsId": 6711, "municipality": "Delémont", "canton": "JU", "cantonId": 26, "income": 150000.0, "values": [23469.0, 23098.0, 22692.0]}, {"bfsId": 6711, "municipality": "Delémont", "canton": "JU", "cantonId": 26, "income": 175000.0, "values": [30840.0, 30388.0, 29900.0]}, {"bfsId": 6711, "municipality": "Delémont", "canton": "JU", "cantonId": 26, "income": 200000.0, "values": [39105.0, 38593.0, 38034.0]}, {"bfsId": 6711, "municipality": "Delémont", "canton": "JU", "cantonId": 26, "income": 250000.0, "values": [56574.0, 55827.0, 55115.0]}, {"bfsId": 6711, "municipality": "Delémont", "canton": "JU", "cantonId": 26, "income": 300000.0, "values": [75194.0, 74265.0, 73403.0]}, {"bfsId": 6711, "municipality": "Delémont", "canton": "JU", "cantonId": 26, "income": 400000.0, "values": [112433.0, 111183.0, 110018.0]}, {"bfsId": 6711, "municipality": "Delémont", "canton": "JU", "cantonId": 26, "income": 500000.0, "values": [149780.0, 148194.0, 146733.0]}, {"bfsId": 6711, "municipality": "Delémont", "canton": "JU", "cantonId": 26, "income": 750000.0, "values": [243928.0, 241465.0, 239293.0]}, {"bfsId": 6711, "municipality": "Delémont", "canton": "JU", "cantonId": 26, "income": 1000000.0, "values": [338075.0, 334736.0, 331812.0]}, {"bfsId": 6711, "municipality": "Delémont", "canton": "JU", "cantonId": 26, "income": 5000000.0, "values": [1789855.0, 1772768.0, 1758075.0]}, {"bfsId": 6711, "municipality": "Delémont", "canton": "JU", "cantonId": 26, "income": 10000000.0, "values": [3604557.0, 3570258.0, 3540840.0]}, {"bfsId": 6711, "municipality": "Delémont", "canton": "JU", "cantonId": 26, "income": 50000000.0, "values": [18122111.0, 17950114.0, 17802962.0]}, {"bfsId": 6711, "municipality": "Delémont", "canton": "JU", "cantonId": 26, "income": 100000000.0, "values": [36269054.0, 35924935.0, 35630614.0]}]}